[
  {
    "symbol": "A",
    "name": null,
    "open": 136.27,
    "high": 139.92,
    "low": 135.54,
    "close": 138.04,
    "volume": 782284,
    "date": "2025-10-14"
  },
  {
    "symbol": "AAPL",
    "name": null,
    "open": 246.6,
    "high": 248.85,
    "low": 244.7,
    "close": 247.77,
    "volume": 33149195,
    "date": "2025-10-14"
  },
  {
    "symbol": "ABBV",
    "name": null,
    "open": 228.07,
    "high": 230.65,
    "low": 227.51,
    "close": 229.13,
    "volume": 4280076,
    "date": "2025-10-14"
  },
  {
    "symbol": "ABNB",
    "name": null,
    "open": 117.69,
    "high": 124.47,
    "low": 117.69,
    "close": 122.89,
    "volume": 5901369,
    "date": "2025-10-14"
  },
  {
    "symbol": "ABT",
    "name": null,
    "open": 131.46,
    "high": 133.34,
    "low": 131.26,
    "close": 133.27,
    "volume": 5713251,
    "date": "2025-10-14"
  },
  {
    "symbol": "ACGL",
    "name": null,
    "open": 92.25,
    "high": 92.81,
    "low": 90.83,
    "close": 92.23,
    "volume": 1811021,
    "date": "2025-10-14"
  },
  {
    "symbol": "ACN",
    "name": null,
    "open": 242.06,
    "high": 246.05,
    "low": 239.57,
    "close": 244.2,
    "volume": 3219783,
    "date": "2025-10-14"
  },
  {
    "symbol": "ADBE",
    "name": null,
    "open": 335.22,
    "high": 338.78,
    "low": 332.72,
    "close": 335.94,
    "volume": 2866883,
    "date": "2025-10-14"
  },
  {
    "symbol": "ADI",
    "name": null,
    "open": 231.15,
    "high": 238.78,
    "low": 229.12,
    "close": 235.4,
    "volume": 3365659,
    "date": "2025-10-14"
  },
  {
    "symbol": "ADM",
    "name": null,
    "open": 60.75,
    "high": 62.38,
    "low": 58.42,
    "close": 61.85,
    "volume": 6045872,
    "date": "2025-10-14"
  },
  {
    "symbol": "ADP",
    "name": null,
    "open": 283.66,
    "high": 286.8,
    "low": 283.66,
    "close": 285.92,
    "volume": 1217300,
    "date": "2025-10-14"
  },
  {
    "symbol": "ADSK",
    "name": null,
    "open": 304.58,
    "high": 308.46,
    "low": 303.12,
    "close": 306.59,
    "volume": 1316797,
    "date": "2025-10-14"
  },
  {
    "symbol": "AEE",
    "name": null,
    "open": 103.85,
    "high": 104.77,
    "low": 103.61,
    "close": 104.23,
    "volume": 1652172,
    "date": "2025-10-14"
  },
  {
    "symbol": "AEP",
    "name": null,
    "open": 117.23,
    "high": 118.68,
    "low": 117.0,
    "close": 118.38,
    "volume": 3188651,
    "date": "2025-10-14"
  },
  {
    "symbol": "AES",
    "name": null,
    "open": 14.3,
    "high": 14.53,
    "low": 14.26,
    "close": 14.39,
    "volume": 7649772,
    "date": "2025-10-14"
  },
  {
    "symbol": "AFL",
    "name": null,
    "open": 110.24,
    "high": 111.56,
    "low": 109.89,
    "close": 111.51,
    "volume": 1090713,
    "date": "2025-10-14"
  },
  {
    "symbol": "AIG",
    "name": null,
    "open": 81.63,
    "high": 83.1,
    "low": 81.37,
    "close": 82.91,
    "volume": 2628121,
    "date": "2025-10-14"
  },
  {
    "symbol": "AIZ",
    "name": null,
    "open": 217.61,
    "high": 223.1,
    "low": 217.61,
    "close": 221.81,
    "volume": 159545,
    "date": "2025-10-14"
  },
  {
    "symbol": "AJG",
    "name": null,
    "open": 298.45,
    "high": 303.98,
    "low": 297.89,
    "close": 303.73,
    "volume": 673669,
    "date": "2025-10-14"
  },
  {
    "symbol": "AKAM",
    "name": null,
    "open": 72.77,
    "high": 74.36,
    "low": 72.49,
    "close": 74.09,
    "volume": 1353159,
    "date": "2025-10-14"
  },
  {
    "symbol": "ALB",
    "name": null,
    "open": 92.65,
    "high": 97.67,
    "low": 91.0,
    "close": 96.24,
    "volume": 3290862,
    "date": "2025-10-14"
  },
  {
    "symbol": "ALGN",
    "name": null,
    "open": 127.07,
    "high": 131.59,
    "low": 126.33,
    "close": 129.79,
    "volume": 1037983,
    "date": "2025-10-14"
  },
  {
    "symbol": "ALL",
    "name": null,
    "open": 206.57,
    "high": 209.89,
    "low": 206.33,
    "close": 209.52,
    "volume": 812843,
    "date": "2025-10-14"
  },
  {
    "symbol": "ALLE",
    "name": null,
    "open": 172.08,
    "high": 176.7,
    "low": 172.82,
    "close": 175.6,
    "volume": 957715,
    "date": "2025-10-14"
  },
  {
    "symbol": "AMAT",
    "name": null,
    "open": 213.9,
    "high": 221.65,
    "low": 213.71,
    "close": 218.19,
    "volume": 8218717,
    "date": "2025-10-14"
  },
  {
    "symbol": "AMCR",
    "name": null,
    "open": 7.91,
    "high": 8.16,
    "low": 7.9,
    "close": 8.1,
    "volume": 19501728,
    "date": "2025-10-14"
  },
  {
    "symbol": "AMD",
    "name": null,
    "open": 219.2,
    "high": 224.98,
    "low": 215.91,
    "close": 218.09,
    "volume": 70507282,
    "date": "2025-10-14"
  },
  {
    "symbol": "AME",
    "name": null,
    "open": 180.69,
    "high": 186.73,
    "low": 180.16,
    "close": 185.78,
    "volume": 1186869,
    "date": "2025-10-14"
  },
  {
    "symbol": "AMGN",
    "name": null,
    "open": 291.74,
    "high": 296.86,
    "low": 290.97,
    "close": 293.85,
    "volume": 1839977,
    "date": "2025-10-14"
  },
  {
    "symbol": "AMP",
    "name": null,
    "open": 477.8,
    "high": 492.48,
    "low": 479.16,
    "close": 486.52,
    "volume": 346300,
    "date": "2025-10-14"
  },
  {
    "symbol": "AMT",
    "name": null,
    "open": 183.81,
    "high": 186.52,
    "low": 183.13,
    "close": 186.51,
    "volume": 4171765,
    "date": "2025-10-14"
  },
  {
    "symbol": "AMZN",
    "name": null,
    "open": 215.55,
    "high": 219.32,
    "low": 212.6,
    "close": 216.39,
    "volume": 43741347,
    "date": "2025-10-14"
  },
  {
    "symbol": "ANET",
    "name": null,
    "open": 142.99,
    "high": 143.02,
    "low": 136.79,
    "close": 138.79,
    "volume": 13488132,
    "date": "2025-10-14"
  },
  {
    "symbol": "AON",
    "name": null,
    "open": 353.78,
    "high": 360.76,
    "low": 352.4,
    "close": 360.51,
    "volume": 845601,
    "date": "2025-10-14"
  },
  {
    "symbol": "AOS",
    "name": null,
    "open": 67.46,
    "high": 69.11,
    "low": 67.24,
    "close": 68.82,
    "volume": 757597,
    "date": "2025-10-14"
  },
  {
    "symbol": "APA",
    "name": null,
    "open": 22.18,
    "high": 23.43,
    "low": 22.11,
    "close": 22.91,
    "volume": 6802061,
    "date": "2025-10-14"
  },
  {
    "symbol": "APD",
    "name": null,
    "open": 258.1,
    "high": 266.1,
    "low": 258.05,
    "close": 262.0,
    "volume": 1009593,
    "date": "2025-10-14"
  },
  {
    "symbol": "APH",
    "name": null,
    "open": 121.73,
    "high": 124.43,
    "low": 120.04,
    "close": 122.64,
    "volume": 4520618,
    "date": "2025-10-14"
  },
  {
    "symbol": "APO",
    "name": null,
    "open": 120.97,
    "high": 128.67,
    "low": 120.57,
    "close": 127.64,
    "volume": 4609657,
    "date": "2025-10-14"
  },
  {
    "symbol": "APP",
    "name": null,
    "open": 576.94,
    "high": 596.75,
    "low": 566.49,
    "close": 590.03,
    "volume": 3459452,
    "date": "2025-10-14"
  },
  {
    "symbol": "APTV",
    "name": null,
    "open": 80.25,
    "high": 83.08,
    "low": 79.96,
    "close": 82.73,
    "volume": 925402,
    "date": "2025-10-14"
  },
  {
    "symbol": "ARE",
    "name": null,
    "open": 73.62,
    "high": 75.36,
    "low": 73.38,
    "close": 75.07,
    "volume": 1092357,
    "date": "2025-10-14"
  },
  {
    "symbol": "ATO",
    "name": null,
    "open": 176.21,
    "high": 177.87,
    "low": 175.4,
    "close": 177.65,
    "volume": 438712,
    "date": "2025-10-14"
  },
  {
    "symbol": "AVB",
    "name": null,
    "open": 184.68,
    "high": 185.96,
    "low": 183.8,
    "close": 185.42,
    "volume": 423459,
    "date": "2025-10-14"
  },
  {
    "symbol": "AVGO",
    "name": null,
    "open": 350.12,
    "high": 350.67,
    "low": 339.65,
    "close": 344.13,
    "volume": 19268034,
    "date": "2025-10-14"
  },
  {
    "symbol": "AVY",
    "name": null,
    "open": 156.7,
    "high": 160.87,
    "low": 156.23,
    "close": 160.13,
    "volume": 577775,
    "date": "2025-10-14"
  },
  {
    "symbol": "AWK",
    "name": null,
    "open": 139.96,
    "high": 143.52,
    "low": 139.5,
    "close": 141.56,
    "volume": 1019863,
    "date": "2025-10-14"
  },
  {
    "symbol": "AXON",
    "name": null,
    "open": 698.68,
    "high": 717.53,
    "low": 690.46,
    "close": 704.67,
    "volume": 342709,
    "date": "2025-10-14"
  },
  {
    "symbol": "AXP",
    "name": null,
    "open": 321.61,
    "high": 336.33,
    "low": 320.5,
    "close": 332.85,
    "volume": 2805884,
    "date": "2025-10-14"
  },
  {
    "symbol": "AZO",
    "name": null,
    "open": 4095.24,
    "high": 4111.01,
    "low": 4051.46,
    "close": 4055.99,
    "volume": 111912,
    "date": "2025-10-14"
  },
  {
    "symbol": "BA",
    "name": null,
    "open": 213.54,
    "high": 217.95,
    "low": 212.24,
    "close": 214.3,
    "volume": 5947476,
    "date": "2025-10-14"
  },
  {
    "symbol": "BAC",
    "name": null,
    "open": 48.85,
    "high": 50.49,
    "low": 48.53,
    "close": 50.09,
    "volume": 36296640,
    "date": "2025-10-14"
  },
  {
    "symbol": "BALL",
    "name": null,
    "open": 46.89,
    "high": 47.81,
    "low": 46.64,
    "close": 47.58,
    "volume": 2767659,
    "date": "2025-10-14"
  },
  {
    "symbol": "BAX",
    "name": null,
    "open": 21.99,
    "high": 22.87,
    "low": 21.9,
    "close": 22.82,
    "volume": 5337777,
    "date": "2025-10-14"
  },
  {
    "symbol": "BBY",
    "name": null,
    "open": 76.24,
    "high": 78.46,
    "low": 75.94,
    "close": 77.21,
    "volume": 4211984,
    "date": "2025-10-14"
  },
  {
    "symbol": "BDX",
    "name": null,
    "open": 185.5,
    "high": 188.79,
    "low": 185.65,
    "close": 188.36,
    "volume": 943927,
    "date": "2025-10-14"
  },
  {
    "symbol": "BEN",
    "name": null,
    "open": 22.57,
    "high": 23.22,
    "low": 22.52,
    "close": 22.92,
    "volume": 4053595,
    "date": "2025-10-14"
  },
  {
    "symbol": "BG",
    "name": null,
    "open": 80.15,
    "high": 82.71,
    "low": 79.11,
    "close": 82.41,
    "volume": 1971630,
    "date": "2025-10-14"
  },
  {
    "symbol": "BIIB",
    "name": null,
    "open": 144.09,
    "high": 146.88,
    "low": 142.2,
    "close": 145.31,
    "volume": 1040131,
    "date": "2025-10-14"
  },
  {
    "symbol": "BK",
    "name": null,
    "open": 105.78,
    "high": 108.2,
    "low": 105.5,
    "close": 107.11,
    "volume": 4086189,
    "date": "2025-10-14"
  },
  {
    "symbol": "BKNG",
    "name": null,
    "open": 5209.68,
    "high": 5318.0,
    "low": 5196.0,
    "close": 5280.14,
    "volume": 149716,
    "date": "2025-10-14"
  },
  {
    "symbol": "BKR",
    "name": null,
    "open": 44.92,
    "high": 45.36,
    "low": 43.92,
    "close": 44.83,
    "volume": 8998809,
    "date": "2025-10-14"
  },
  {
    "symbol": "BLDR",
    "name": null,
    "open": 119.5,
    "high": 128.71,
    "low": 119.0,
    "close": 128.09,
    "volume": 1893589,
    "date": "2025-10-14"
  },
  {
    "symbol": "BLK",
    "name": null,
    "open": 1140.0,
    "high": 1209.82,
    "low": 1135.0,
    "close": 1194.26,
    "volume": 1055234,
    "date": "2025-10-14"
  },
  {
    "symbol": "BMY",
    "name": null,
    "open": 43.43,
    "high": 43.9,
    "low": 43.27,
    "close": 43.8,
    "volume": 13302304,
    "date": "2025-10-14"
  },
  {
    "symbol": "BR",
    "name": null,
    "open": 232.83,
    "high": 235.68,
    "low": 232.44,
    "close": 235.01,
    "volume": 308616,
    "date": "2025-10-14"
  },
  {
    "symbol": "BRO",
    "name": null,
    "open": 94.56,
    "high": 94.96,
    "low": 93.79,
    "close": 94.77,
    "volume": 1366980,
    "date": "2025-10-14"
  },
  {
    "symbol": "BSX",
    "name": null,
    "open": 94.71,
    "high": 96.41,
    "low": 94.53,
    "close": 96.24,
    "volume": 4945177,
    "date": "2025-10-14"
  },
  {
    "symbol": "BX",
    "name": null,
    "open": 156.17,
    "high": 165.09,
    "low": 156.5,
    "close": 163.98,
    "volume": 4644464,
    "date": "2025-10-14"
  },
  {
    "symbol": "BXP",
    "name": null,
    "open": 69.58,
    "high": 70.59,
    "low": 69.44,
    "close": 70.53,
    "volume": 1984732,
    "date": "2025-10-14"
  },
  {
    "symbol": "C",
    "name": null,
    "open": 95.37,
    "high": 101.22,
    "low": 95.04,
    "close": 99.84,
    "volume": 27039349,
    "date": "2025-10-14"
  },
  {
    "symbol": "CAG",
    "name": null,
    "open": 18.15,
    "high": 18.52,
    "low": 18.07,
    "close": 18.5,
    "volume": 15007882,
    "date": "2025-10-14"
  },
  {
    "symbol": "CAH",
    "name": null,
    "open": 154.34,
    "high": 154.42,
    "low": 151.87,
    "close": 154.19,
    "volume": 1811559,
    "date": "2025-10-14"
  },
  {
    "symbol": "CARR",
    "name": null,
    "open": 55.53,
    "high": 57.88,
    "low": 55.33,
    "close": 57.5,
    "volume": 5413788,
    "date": "2025-10-14"
  },
  {
    "symbol": "CAT",
    "name": null,
    "open": 500.58,
    "high": 531.56,
    "low": 499.01,
    "close": 527.47,
    "volume": 5425489,
    "date": "2025-10-14"
  },
  {
    "symbol": "CB",
    "name": null,
    "open": 283.32,
    "high": 285.62,
    "low": 281.92,
    "close": 284.63,
    "volume": 1034320,
    "date": "2025-10-14"
  },
  {
    "symbol": "CBOE",
    "name": null,
    "open": 243.89,
    "high": 246.64,
    "low": 237.41,
    "close": 238.21,
    "volume": 757062,
    "date": "2025-10-14"
  },
  {
    "symbol": "CBRE",
    "name": null,
    "open": 151.88,
    "high": 154.85,
    "low": 151.51,
    "close": 154.36,
    "volume": 979240,
    "date": "2025-10-14"
  },
  {
    "symbol": "CCI",
    "name": null,
    "open": 96.18,
    "high": 97.63,
    "low": 95.99,
    "close": 97.29,
    "volume": 1874372,
    "date": "2025-10-14"
  },
  {
    "symbol": "CCL",
    "name": null,
    "open": 27.64,
    "high": 29.27,
    "low": 27.47,
    "close": 28.96,
    "volume": 15973974,
    "date": "2025-10-14"
  },
  {
    "symbol": "CDNS",
    "name": null,
    "open": 324.5,
    "high": 329.85,
    "low": 318.02,
    "close": 325.75,
    "volume": 1527109,
    "date": "2025-10-14"
  },
  {
    "symbol": "CDW",
    "name": null,
    "open": 145.83,
    "high": 151.07,
    "low": 145.83,
    "close": 150.33,
    "volume": 1286596,
    "date": "2025-10-14"
  },
  {
    "symbol": "CEG",
    "name": null,
    "open": 374.7,
    "high": 395.14,
    "low": 366.16,
    "close": 389.56,
    "volume": 3090003,
    "date": "2025-10-14"
  },
  {
    "symbol": "CF",
    "name": null,
    "open": 88.03,
    "high": 88.42,
    "low": 85.42,
    "close": 86.73,
    "volume": 1345924,
    "date": "2025-10-14"
  },
  {
    "symbol": "CFG",
    "name": null,
    "open": 50.0,
    "high": 51.99,
    "low": 50.0,
    "close": 51.8,
    "volume": 4837669,
    "date": "2025-10-14"
  },
  {
    "symbol": "CHD",
    "name": null,
    "open": 86.99,
    "high": 87.18,
    "low": 86.14,
    "close": 86.93,
    "volume": 986793,
    "date": "2025-10-14"
  },
  {
    "symbol": "CHRW",
    "name": null,
    "open": 124.39,
    "high": 128.13,
    "low": 123.64,
    "close": 127.98,
    "volume": 1369304,
    "date": "2025-10-14"
  },
  {
    "symbol": "CHTR",
    "name": null,
    "open": 258.99,
    "high": 268.77,
    "low": 258.88,
    "close": 266.25,
    "volume": 1350966,
    "date": "2025-10-14"
  },
  {
    "symbol": "CI",
    "name": null,
    "open": 296.33,
    "high": 303.88,
    "low": 296.12,
    "close": 302.13,
    "volume": 843583,
    "date": "2025-10-14"
  },
  {
    "symbol": "CINF",
    "name": null,
    "open": 157.42,
    "high": 159.29,
    "low": 157.14,
    "close": 158.75,
    "volume": 466214,
    "date": "2025-10-14"
  },
  {
    "symbol": "CL",
    "name": null,
    "open": 77.13,
    "high": 78.47,
    "low": 76.91,
    "close": 78.4,
    "volume": 4611080,
    "date": "2025-10-14"
  },
  {
    "symbol": "CLX",
    "name": null,
    "open": 120.76,
    "high": 120.83,
    "low": 117.22,
    "close": 119.33,
    "volume": 1604207,
    "date": "2025-10-14"
  },
  {
    "symbol": "CMCSA",
    "name": null,
    "open": 29.45,
    "high": 30.11,
    "low": 29.41,
    "close": 29.99,
    "volume": 17353520,
    "date": "2025-10-14"
  },
  {
    "symbol": "CME",
    "name": null,
    "open": 273.54,
    "high": 275.37,
    "low": 266.55,
    "close": 267.18,
    "volume": 1678351,
    "date": "2025-10-14"
  },
  {
    "symbol": "CMG",
    "name": null,
    "open": 40.3,
    "high": 42.6,
    "low": 40.06,
    "close": 42.1,
    "volume": 18176580,
    "date": "2025-10-14"
  },
  {
    "symbol": "CMI",
    "name": null,
    "open": 403.1,
    "high": 421.27,
    "low": 400.72,
    "close": 416.65,
    "volume": 714659,
    "date": "2025-10-14"
  },
  {
    "symbol": "CMS",
    "name": null,
    "open": 73.84,
    "high": 74.9,
    "low": 73.6,
    "close": 74.35,
    "volume": 977999,
    "date": "2025-10-14"
  },
  {
    "symbol": "CNC",
    "name": null,
    "open": 35.83,
    "high": 36.66,
    "low": 35.28,
    "close": 36.44,
    "volume": 6022438,
    "date": "2025-10-14"
  },
  {
    "symbol": "CNP",
    "name": null,
    "open": 39.3,
    "high": 39.65,
    "low": 39.25,
    "close": 39.49,
    "volume": 3622518,
    "date": "2025-10-14"
  },
  {
    "symbol": "COF",
    "name": null,
    "open": 206.12,
    "high": 216.72,
    "low": 206.25,
    "close": 214.2,
    "volume": 3997449,
    "date": "2025-10-14"
  },
  {
    "symbol": "COIN",
    "name": null,
    "open": 340.85,
    "high": 353.5,
    "low": 334.77,
    "close": 341.55,
    "volume": 9388226,
    "date": "2025-10-14"
  },
  {
    "symbol": "COO",
    "name": null,
    "open": 68.72,
    "high": 71.97,
    "low": 68.36,
    "close": 71.21,
    "volume": 2138762,
    "date": "2025-10-14"
  },
  {
    "symbol": "COP",
    "name": null,
    "open": 86.9,
    "high": 88.89,
    "low": 86.75,
    "close": 88.17,
    "volume": 4324984,
    "date": "2025-10-14"
  },
  {
    "symbol": "COR",
    "name": null,
    "open": 318.95,
    "high": 319.39,
    "low": 314.5,
    "close": 317.93,
    "volume": 516108,
    "date": "2025-10-14"
  },
  {
    "symbol": "COST",
    "name": null,
    "open": 940.26,
    "high": 947.34,
    "low": 935.95,
    "close": 946.51,
    "volume": 1898042,
    "date": "2025-10-14"
  },
  {
    "symbol": "CPAY",
    "name": null,
    "open": 279.68,
    "high": 290.91,
    "low": 278.34,
    "close": 289.82,
    "volume": 276540,
    "date": "2025-10-14"
  },
  {
    "symbol": "CPB",
    "name": null,
    "open": 29.82,
    "high": 30.38,
    "low": 29.69,
    "close": 30.34,
    "volume": 5576457,
    "date": "2025-10-14"
  },
  {
    "symbol": "CPRT",
    "name": null,
    "open": 44.01,
    "high": 44.92,
    "low": 43.99,
    "close": 44.77,
    "volume": 4467773,
    "date": "2025-10-14"
  },
  {
    "symbol": "CPT",
    "name": null,
    "open": 101.69,
    "high": 102.43,
    "low": 100.64,
    "close": 102.13,
    "volume": 1151894,
    "date": "2025-10-14"
  },
  {
    "symbol": "CRL",
    "name": null,
    "open": 168.43,
    "high": 172.41,
    "low": 166.93,
    "close": 170.13,
    "volume": 476822,
    "date": "2025-10-14"
  },
  {
    "symbol": "CRM",
    "name": null,
    "open": 248.11,
    "high": 248.28,
    "low": 239.56,
    "close": 239.77,
    "volume": 7905992,
    "date": "2025-10-14"
  },
  {
    "symbol": "CRWD",
    "name": null,
    "open": 500.1,
    "high": 500.54,
    "low": 487.59,
    "close": 488.94,
    "volume": 2648165,
    "date": "2025-10-14"
  },
  {
    "symbol": "CSCO",
    "name": null,
    "open": 67.11,
    "high": 69.16,
    "low": 66.81,
    "close": 68.66,
    "volume": 13053214,
    "date": "2025-10-14"
  },
  {
    "symbol": "CSGP",
    "name": null,
    "open": 74.56,
    "high": 76.09,
    "low": 74.51,
    "close": 75.73,
    "volume": 3293928,
    "date": "2025-10-14"
  },
  {
    "symbol": "CSX",
    "name": null,
    "open": 35.31,
    "high": 36.17,
    "low": 35.18,
    "close": 36.13,
    "volume": 12069193,
    "date": "2025-10-14"
  },
  {
    "symbol": "CTAS",
    "name": null,
    "open": 186.97,
    "high": 189.48,
    "low": 185.52,
    "close": 188.23,
    "volume": 2438618,
    "date": "2025-10-14"
  },
  {
    "symbol": "CTRA",
    "name": null,
    "open": 22.81,
    "high": 23.37,
    "low": 22.61,
    "close": 23.21,
    "volume": 11006827,
    "date": "2025-10-14"
  },
  {
    "symbol": "CTSH",
    "name": null,
    "open": 65.76,
    "high": 67.69,
    "low": 65.6,
    "close": 67.27,
    "volume": 3972066,
    "date": "2025-10-14"
  },
  {
    "symbol": "CTVA",
    "name": null,
    "open": 62.46,
    "high": 62.76,
    "low": 62.04,
    "close": 62.67,
    "volume": 3089791,
    "date": "2025-10-14"
  },
  {
    "symbol": "CVS",
    "name": null,
    "open": 78.31,
    "high": 79.94,
    "low": 77.8,
    "close": 79.66,
    "volume": 9395329,
    "date": "2025-10-14"
  },
  {
    "symbol": "CVX",
    "name": null,
    "open": 149.81,
    "high": 153.46,
    "low": 149.66,
    "close": 152.39,
    "volume": 5005789,
    "date": "2025-10-14"
  },
  {
    "symbol": "D",
    "name": null,
    "open": 61.4,
    "high": 61.85,
    "low": 61.23,
    "close": 61.52,
    "volume": 3766389,
    "date": "2025-10-14"
  },
  {
    "symbol": "DAL",
    "name": null,
    "open": 57.8,
    "high": 61.8,
    "low": 57.68,
    "close": 61.27,
    "volume": 10913730,
    "date": "2025-10-14"
  },
  {
    "symbol": "DASH",
    "name": null,
    "open": 272.91,
    "high": 275.55,
    "low": 267.04,
    "close": 270.54,
    "volume": 1957561,
    "date": "2025-10-14"
  },
  {
    "symbol": "DAY",
    "name": null,
    "open": 68.22,
    "high": 68.4,
    "low": 68.15,
    "close": 68.2,
    "volume": 1833528,
    "date": "2025-10-14"
  },
  {
    "symbol": "DD",
    "name": null,
    "open": 74.73,
    "high": 77.84,
    "low": 74.66,
    "close": 77.58,
    "volume": 2203932,
    "date": "2025-10-14"
  },
  {
    "symbol": "DDOG",
    "name": null,
    "open": 160.63,
    "high": 162.14,
    "low": 158.3,
    "close": 160.88,
    "volume": 2818923,
    "date": "2025-10-14"
  },
  {
    "symbol": "DE",
    "name": null,
    "open": 436.08,
    "high": 449.83,
    "low": 433.0,
    "close": 447.95,
    "volume": 1258255,
    "date": "2025-10-14"
  },
  {
    "symbol": "DECK",
    "name": null,
    "open": 97.0,
    "high": 99.67,
    "low": 96.45,
    "close": 99.28,
    "volume": 2504452,
    "date": "2025-10-14"
  },
  {
    "symbol": "DELL",
    "name": null,
    "open": 149.98,
    "high": 152.56,
    "low": 148.1,
    "close": 148.77,
    "volume": 6501908,
    "date": "2025-10-14"
  },
  {
    "symbol": "DG",
    "name": null,
    "open": 102.25,
    "high": 103.94,
    "low": 101.1,
    "close": 103.71,
    "volume": 2632992,
    "date": "2025-10-14"
  },
  {
    "symbol": "DGX",
    "name": null,
    "open": 182.82,
    "high": 185.7,
    "low": 182.77,
    "close": 185.39,
    "volume": 531750,
    "date": "2025-10-14"
  },
  {
    "symbol": "DHI",
    "name": null,
    "open": 152.06,
    "high": 158.56,
    "low": 151.82,
    "close": 156.74,
    "volume": 3241873,
    "date": "2025-10-14"
  },
  {
    "symbol": "DHR",
    "name": null,
    "open": 202.88,
    "high": 207.32,
    "low": 202.33,
    "close": 206.15,
    "volume": 1693748,
    "date": "2025-10-14"
  },
  {
    "symbol": "DIS",
    "name": null,
    "open": 109.65,
    "high": 111.84,
    "low": 109.2,
    "close": 111.17,
    "volume": 6318036,
    "date": "2025-10-14"
  },
  {
    "symbol": "DLR",
    "name": null,
    "open": 170.1,
    "high": 172.32,
    "low": 169.45,
    "close": 171.88,
    "volume": 777519,
    "date": "2025-10-14"
  },
  {
    "symbol": "DLTR",
    "name": null,
    "open": 92.62,
    "high": 96.18,
    "low": 92.24,
    "close": 95.58,
    "volume": 6989567,
    "date": "2025-10-14"
  },
  {
    "symbol": "DOC",
    "name": null,
    "open": 17.8,
    "high": 18.18,
    "low": 17.51,
    "close": 18.14,
    "volume": 18527371,
    "date": "2025-10-14"
  },
  {
    "symbol": "DOV",
    "name": null,
    "open": 159.18,
    "high": 163.67,
    "low": 158.97,
    "close": 162.55,
    "volume": 892198,
    "date": "2025-10-14"
  },
  {
    "symbol": "DOW",
    "name": null,
    "open": 21.01,
    "high": 22.09,
    "low": 20.9,
    "close": 21.92,
    "volume": 8559549,
    "date": "2025-10-14"
  },
  {
    "symbol": "DPZ",
    "name": null,
    "open": 407.24,
    "high": 428.26,
    "low": 398.81,
    "close": 424.23,
    "volume": 1603671,
    "date": "2025-10-14"
  },
  {
    "symbol": "DRI",
    "name": null,
    "open": 183.74,
    "high": 187.97,
    "low": 183.48,
    "close": 187.0,
    "volume": 920338,
    "date": "2025-10-14"
  },
  {
    "symbol": "DTE",
    "name": null,
    "open": 140.16,
    "high": 142.47,
    "low": 140.16,
    "close": 141.65,
    "volume": 807243,
    "date": "2025-10-14"
  },
  {
    "symbol": "DUK",
    "name": null,
    "open": 126.91,
    "high": 128.49,
    "low": 126.29,
    "close": 127.82,
    "volume": 1996232,
    "date": "2025-10-14"
  },
  {
    "symbol": "DVA",
    "name": null,
    "open": 123.46,
    "high": 126.94,
    "low": 123.1,
    "close": 126.62,
    "volume": 653926,
    "date": "2025-10-14"
  },
  {
    "symbol": "DVN",
    "name": null,
    "open": 32.42,
    "high": 33.12,
    "low": 32.26,
    "close": 32.71,
    "volume": 6947715,
    "date": "2025-10-14"
  },
  {
    "symbol": "DXCM",
    "name": null,
    "open": 63.85,
    "high": 67.29,
    "low": 63.19,
    "close": 66.21,
    "volume": 5710254,
    "date": "2025-10-14"
  },
  {
    "symbol": "EA",
    "name": null,
    "open": 200.11,
    "high": 200.78,
    "low": 200.04,
    "close": 200.2,
    "volume": 3137991,
    "date": "2025-10-14"
  },
  {
    "symbol": "EBAY",
    "name": null,
    "open": 88.75,
    "high": 91.64,
    "low": 88.02,
    "close": 91.06,
    "volume": 4193919,
    "date": "2025-10-14"
  },
  {
    "symbol": "ECL",
    "name": null,
    "open": 269.78,
    "high": 274.3,
    "low": 269.11,
    "close": 273.03,
    "volume": 970775,
    "date": "2025-10-14"
  },
  {
    "symbol": "ED",
    "name": null,
    "open": 101.71,
    "high": 102.7,
    "low": 101.33,
    "close": 101.89,
    "volume": 1111252,
    "date": "2025-10-14"
  },
  {
    "symbol": "EFX",
    "name": null,
    "open": 223.76,
    "high": 228.86,
    "low": 221.6,
    "close": 228.33,
    "volume": 979017,
    "date": "2025-10-14"
  },
  {
    "symbol": "EG",
    "name": null,
    "open": 351.18,
    "high": 356.94,
    "low": 347.96,
    "close": 356.74,
    "volume": 187646,
    "date": "2025-10-14"
  },
  {
    "symbol": "EIX",
    "name": null,
    "open": 53.69,
    "high": 56.22,
    "low": 53.6,
    "close": 56.07,
    "volume": 3661427,
    "date": "2025-10-14"
  },
  {
    "symbol": "EL",
    "name": null,
    "open": 91.24,
    "high": 96.18,
    "low": 91.1,
    "close": 95.0,
    "volume": 3349240,
    "date": "2025-10-14"
  },
  {
    "symbol": "ELV",
    "name": null,
    "open": 345.12,
    "high": 351.43,
    "low": 344.37,
    "close": 350.48,
    "volume": 1251499,
    "date": "2025-10-14"
  },
  {
    "symbol": "EME",
    "name": null,
    "open": 668.0,
    "high": 681.02,
    "low": 661.01,
    "close": 674.14,
    "volume": 451923,
    "date": "2025-10-14"
  },
  {
    "symbol": "EMN",
    "name": null,
    "open": 58.85,
    "high": 60.96,
    "low": 58.41,
    "close": 60.54,
    "volume": 1254635,
    "date": "2025-10-14"
  },
  {
    "symbol": "EMR",
    "name": null,
    "open": 126.0,
    "high": 131.32,
    "low": 125.71,
    "close": 129.77,
    "volume": 1559340,
    "date": "2025-10-14"
  },
  {
    "symbol": "EOG",
    "name": null,
    "open": 107.59,
    "high": 110.43,
    "low": 107.53,
    "close": 109.12,
    "volume": 2261152,
    "date": "2025-10-14"
  },
  {
    "symbol": "EPAM",
    "name": null,
    "open": 144.3,
    "high": 148.73,
    "low": 143.26,
    "close": 146.98,
    "volume": 423262,
    "date": "2025-10-14"
  },
  {
    "symbol": "EQIX",
    "name": null,
    "open": 804.79,
    "high": 822.53,
    "low": 802.97,
    "close": 817.42,
    "volume": 501375,
    "date": "2025-10-14"
  },
  {
    "symbol": "EQR",
    "name": null,
    "open": 61.96,
    "high": 62.35,
    "low": 61.73,
    "close": 62.3,
    "volume": 1093511,
    "date": "2025-10-14"
  },
  {
    "symbol": "EQT",
    "name": null,
    "open": 52.74,
    "high": 53.83,
    "low": 51.66,
    "close": 53.29,
    "volume": 5440461,
    "date": "2025-10-14"
  },
  {
    "symbol": "ERIE",
    "name": null,
    "open": 319.23,
    "high": 322.72,
    "low": 314.99,
    "close": 321.14,
    "volume": 89933,
    "date": "2025-10-14"
  },
  {
    "symbol": "ES",
    "name": null,
    "open": 70.8,
    "high": 71.3,
    "low": 70.33,
    "close": 70.59,
    "volume": 2259972,
    "date": "2025-10-14"
  },
  {
    "symbol": "ESS",
    "name": null,
    "open": 257.33,
    "high": 259.46,
    "low": 255.71,
    "close": 259.37,
    "volume": 430070,
    "date": "2025-10-14"
  },
  {
    "symbol": "ETN",
    "name": null,
    "open": 368.73,
    "high": 379.15,
    "low": 364.36,
    "close": 374.35,
    "volume": 1348067,
    "date": "2025-10-14"
  },
  {
    "symbol": "ETR",
    "name": null,
    "open": 95.55,
    "high": 97.29,
    "low": 95.31,
    "close": 96.66,
    "volume": 2024033,
    "date": "2025-10-14"
  },
  {
    "symbol": "EVRG",
    "name": null,
    "open": 77.71,
    "high": 78.33,
    "low": 77.5,
    "close": 78.09,
    "volume": 1453063,
    "date": "2025-10-14"
  },
  {
    "symbol": "EW",
    "name": null,
    "open": 72.77,
    "high": 73.52,
    "low": 72.47,
    "close": 73.36,
    "volume": 2831974,
    "date": "2025-10-14"
  },
  {
    "symbol": "EXC",
    "name": null,
    "open": 47.32,
    "high": 47.63,
    "low": 47.17,
    "close": 47.38,
    "volume": 4963331,
    "date": "2025-10-14"
  },
  {
    "symbol": "EXE",
    "name": null,
    "open": 100.69,
    "high": 101.93,
    "low": 98.71,
    "close": 101.36,
    "volume": 2395708,
    "date": "2025-10-14"
  },
  {
    "symbol": "EXPD",
    "name": null,
    "open": 113.89,
    "high": 118.08,
    "low": 113.51,
    "close": 117.39,
    "volume": 1076468,
    "date": "2025-10-14"
  },
  {
    "symbol": "EXPE",
    "name": null,
    "open": 212.12,
    "high": 224.56,
    "low": 212.12,
    "close": 223.12,
    "volume": 1453762,
    "date": "2025-10-14"
  },
  {
    "symbol": "EXR",
    "name": null,
    "open": 145.44,
    "high": 148.65,
    "low": 144.73,
    "close": 147.84,
    "volume": 1108843,
    "date": "2025-10-14"
  },
  {
    "symbol": "F",
    "name": null,
    "open": 11.38,
    "high": 11.76,
    "low": 11.34,
    "close": 11.65,
    "volume": 85763939,
    "date": "2025-10-14"
  },
  {
    "symbol": "FANG",
    "name": null,
    "open": 139.39,
    "high": 143.1,
    "low": 139.0,
    "close": 141.83,
    "volume": 1647978,
    "date": "2025-10-14"
  },
  {
    "symbol": "FAST",
    "name": null,
    "open": 41.92,
    "high": 43.49,
    "low": 41.46,
    "close": 42.75,
    "volume": 14609239,
    "date": "2025-10-14"
  },
  {
    "symbol": "FCX",
    "name": null,
    "open": 41.56,
    "high": 42.43,
    "low": 40.5,
    "close": 41.97,
    "volume": 14545773,
    "date": "2025-10-14"
  },
  {
    "symbol": "FDS",
    "name": null,
    "open": 285.0,
    "high": 289.46,
    "low": 281.04,
    "close": 285.75,
    "volume": 842398,
    "date": "2025-10-14"
  },
  {
    "symbol": "FDX",
    "name": null,
    "open": 228.0,
    "high": 235.1,
    "low": 227.01,
    "close": 234.67,
    "volume": 974712,
    "date": "2025-10-14"
  },
  {
    "symbol": "FE",
    "name": null,
    "open": 47.09,
    "high": 47.65,
    "low": 47.02,
    "close": 47.53,
    "volume": 3754135,
    "date": "2025-10-14"
  },
  {
    "symbol": "FFIV",
    "name": null,
    "open": 336.88,
    "high": 345.47,
    "low": 335.12,
    "close": 343.17,
    "volume": 722704,
    "date": "2025-10-14"
  },
  {
    "symbol": "FI",
    "name": null,
    "open": 121.78,
    "high": 124.53,
    "low": 121.4,
    "close": 124.12,
    "volume": 3919816,
    "date": "2025-10-14"
  },
  {
    "symbol": "FICO",
    "name": null,
    "open": 1641.71,
    "high": 1655.81,
    "low": 1581.48,
    "close": 1649.51,
    "volume": 345183,
    "date": "2025-10-14"
  },
  {
    "symbol": "FIS",
    "name": null,
    "open": 67.07,
    "high": 68.5,
    "low": 67.06,
    "close": 67.74,
    "volume": 3022803,
    "date": "2025-10-14"
  },
  {
    "symbol": "FITB",
    "name": null,
    "open": 42.23,
    "high": 43.71,
    "low": 42.01,
    "close": 43.41,
    "volume": 7537215,
    "date": "2025-10-14"
  },
  {
    "symbol": "FOX",
    "name": null,
    "open": 51.57,
    "high": 52.22,
    "low": 51.27,
    "close": 52.11,
    "volume": 899017,
    "date": "2025-10-14"
  },
  {
    "symbol": "FOXA",
    "name": null,
    "open": 57.75,
    "high": 58.25,
    "low": 57.25,
    "close": 58.11,
    "volume": 2182032,
    "date": "2025-10-14"
  },
  {
    "symbol": "FRT",
    "name": null,
    "open": 96.96,
    "high": 97.56,
    "low": 96.44,
    "close": 97.34,
    "volume": 381684,
    "date": "2025-10-14"
  },
  {
    "symbol": "FSLR",
    "name": null,
    "open": 224.26,
    "high": 230.96,
    "low": 220.1,
    "close": 224.43,
    "volume": 2068754,
    "date": "2025-10-14"
  },
  {
    "symbol": "FTNT",
    "name": null,
    "open": 82.5,
    "high": 83.9,
    "low": 82.2,
    "close": 83.08,
    "volume": 4808377,
    "date": "2025-10-14"
  },
  {
    "symbol": "FTV",
    "name": null,
    "open": 47.95,
    "high": 49.31,
    "low": 47.95,
    "close": 49.03,
    "volume": 1011412,
    "date": "2025-10-14"
  },
  {
    "symbol": "GD",
    "name": null,
    "open": 333.63,
    "high": 338.78,
    "low": 333.0,
    "close": 335.5,
    "volume": 530332,
    "date": "2025-10-14"
  },
  {
    "symbol": "GDDY",
    "name": null,
    "open": 131.18,
    "high": 133.99,
    "low": 130.43,
    "close": 132.27,
    "volume": 819565,
    "date": "2025-10-14"
  },
  {
    "symbol": "GE",
    "name": null,
    "open": 294.84,
    "high": 302.27,
    "low": 292.01,
    "close": 300.08,
    "volume": 2021913,
    "date": "2025-10-14"
  },
  {
    "symbol": "GEHC",
    "name": null,
    "open": 71.17,
    "high": 73.1,
    "low": 70.98,
    "close": 72.34,
    "volume": 2741928,
    "date": "2025-10-14"
  },
  {
    "symbol": "GEN",
    "name": null,
    "open": 26.6,
    "high": 27.0,
    "low": 26.38,
    "close": 26.83,
    "volume": 2970688,
    "date": "2025-10-14"
  },
  {
    "symbol": "GEV",
    "name": null,
    "open": 635.0,
    "high": 656.88,
    "low": 615.85,
    "close": 644.41,
    "volume": 2383047,
    "date": "2025-10-14"
  },
  {
    "symbol": "GILD",
    "name": null,
    "open": 117.51,
    "high": 119.33,
    "low": 116.62,
    "close": 118.48,
    "volume": 6220906,
    "date": "2025-10-14"
  },
  {
    "symbol": "GIS",
    "name": null,
    "open": 48.01,
    "high": 48.9,
    "low": 47.71,
    "close": 48.58,
    "volume": 4956229,
    "date": "2025-10-14"
  },
  {
    "symbol": "GL",
    "name": null,
    "open": 136.4,
    "high": 140.26,
    "low": 136.46,
    "close": 139.87,
    "volume": 439605,
    "date": "2025-10-14"
  },
  {
    "symbol": "GLW",
    "name": null,
    "open": 84.28,
    "high": 85.91,
    "low": 83.61,
    "close": 84.61,
    "volume": 4260444,
    "date": "2025-10-14"
  },
  {
    "symbol": "GM",
    "name": null,
    "open": 54.51,
    "high": 57.25,
    "low": 54.33,
    "close": 57.15,
    "volume": 6761434,
    "date": "2025-10-14"
  },
  {
    "symbol": "GNRC",
    "name": null,
    "open": 171.27,
    "high": 184.59,
    "low": 170.52,
    "close": 183.82,
    "volume": 1418344,
    "date": "2025-10-14"
  },
  {
    "symbol": "GOOG",
    "name": null,
    "open": 241.86,
    "high": 248.02,
    "low": 241.18,
    "close": 246.19,
    "volume": 16534097,
    "date": "2025-10-14"
  },
  {
    "symbol": "GOOGL",
    "name": null,
    "open": 241.23,
    "high": 247.12,
    "low": 240.52,
    "close": 245.45,
    "volume": 21933543,
    "date": "2025-10-14"
  },
  {
    "symbol": "GPC",
    "name": null,
    "open": 131.31,
    "high": 133.99,
    "low": 130.86,
    "close": 133.66,
    "volume": 584917,
    "date": "2025-10-14"
  },
  {
    "symbol": "GPN",
    "name": null,
    "open": 83.18,
    "high": 86.92,
    "low": 83.09,
    "close": 86.47,
    "volume": 1263237,
    "date": "2025-10-14"
  },
  {
    "symbol": "GRMN",
    "name": null,
    "open": 248.45,
    "high": 252.51,
    "low": 247.5,
    "close": 249.33,
    "volume": 503053,
    "date": "2025-10-14"
  },
  {
    "symbol": "GS",
    "name": null,
    "open": 764.45,
    "high": 786.53,
    "low": 742.46,
    "close": 770.76,
    "volume": 4407349,
    "date": "2025-10-14"
  },
  {
    "symbol": "GWW",
    "name": null,
    "open": 933.15,
    "high": 964.02,
    "low": 925.41,
    "close": 959.74,
    "volume": 238427,
    "date": "2025-10-14"
  },
  {
    "symbol": "HAL",
    "name": null,
    "open": 22.01,
    "high": 22.66,
    "low": 21.91,
    "close": 22.44,
    "volume": 8596118,
    "date": "2025-10-14"
  },
  {
    "symbol": "HAS",
    "name": null,
    "open": 71.88,
    "high": 73.56,
    "low": 71.25,
    "close": 73.14,
    "volume": 1322846,
    "date": "2025-10-14"
  },
  {
    "symbol": "HBAN",
    "name": null,
    "open": 15.85,
    "high": 16.46,
    "low": 15.77,
    "close": 16.34,
    "volume": 26372506,
    "date": "2025-10-14"
  },
  {
    "symbol": "HCA",
    "name": null,
    "open": 410.0,
    "high": 420.58,
    "low": 409.11,
    "close": 418.4,
    "volume": 1138472,
    "date": "2025-10-14"
  },
  {
    "symbol": "HD",
    "name": null,
    "open": 378.87,
    "high": 388.89,
    "low": 378.01,
    "close": 387.72,
    "volume": 2993055,
    "date": "2025-10-14"
  },
  {
    "symbol": "HIG",
    "name": null,
    "open": 129.05,
    "high": 131.4,
    "low": 128.87,
    "close": 131.18,
    "volume": 1041389,
    "date": "2025-10-14"
  },
  {
    "symbol": "HII",
    "name": null,
    "open": 288.21,
    "high": 296.03,
    "low": 284.02,
    "close": 291.94,
    "volume": 586296,
    "date": "2025-10-14"
  },
  {
    "symbol": "HLT",
    "name": null,
    "open": 261.54,
    "high": 268.65,
    "low": 261.39,
    "close": 268.4,
    "volume": 754343,
    "date": "2025-10-14"
  },
  {
    "symbol": "HOLX",
    "name": null,
    "open": 65.49,
    "high": 66.29,
    "low": 65.0,
    "close": 65.92,
    "volume": 988107,
    "date": "2025-10-14"
  },
  {
    "symbol": "HON",
    "name": null,
    "open": 201.42,
    "high": 208.73,
    "low": 201.35,
    "close": 208.61,
    "volume": 4035167,
    "date": "2025-10-14"
  },
  {
    "symbol": "HOOD",
    "name": null,
    "open": 136.67,
    "high": 141.21,
    "low": 133.05,
    "close": 134.95,
    "volume": 30043039,
    "date": "2025-10-14"
  },
  {
    "symbol": "HPE",
    "name": null,
    "open": 24.38,
    "high": 25.37,
    "low": 24.28,
    "close": 25.0,
    "volume": 32353697,
    "date": "2025-10-14"
  },
  {
    "symbol": "HPQ",
    "name": null,
    "open": 27.49,
    "high": 28.74,
    "low": 27.4,
    "close": 28.54,
    "volume": 18920097,
    "date": "2025-10-14"
  },
  {
    "symbol": "HRL",
    "name": null,
    "open": 23.2,
    "high": 23.95,
    "low": 23.13,
    "close": 23.92,
    "volume": 3974056,
    "date": "2025-10-14"
  },
  {
    "symbol": "HSIC",
    "name": null,
    "open": 62.29,
    "high": 63.81,
    "low": 62.25,
    "close": 63.39,
    "volume": 1541755,
    "date": "2025-10-14"
  },
  {
    "symbol": "HST",
    "name": null,
    "open": 16.02,
    "high": 16.46,
    "low": 15.95,
    "close": 16.38,
    "volume": 6390702,
    "date": "2025-10-14"
  },
  {
    "symbol": "HSY",
    "name": null,
    "open": 188.6,
    "high": 191.45,
    "low": 184.53,
    "close": 189.43,
    "volume": 1453088,
    "date": "2025-10-14"
  },
  {
    "symbol": "HUBB",
    "name": null,
    "open": 412.94,
    "high": 433.62,
    "low": 412.52,
    "close": 427.43,
    "volume": 514142,
    "date": "2025-10-14"
  },
  {
    "symbol": "HUM",
    "name": null,
    "open": 266.11,
    "high": 268.0,
    "low": 257.94,
    "close": 261.61,
    "volume": 2518170,
    "date": "2025-10-14"
  },
  {
    "symbol": "HWM",
    "name": null,
    "open": 188.0,
    "high": 194.95,
    "low": 186.88,
    "close": 193.03,
    "volume": 1486758,
    "date": "2025-10-14"
  },
  {
    "symbol": "IBKR",
    "name": null,
    "open": 69.32,
    "high": 71.14,
    "low": 68.11,
    "close": 69.36,
    "volume": 4569659,
    "date": "2025-10-14"
  },
  {
    "symbol": "IBM",
    "name": null,
    "open": 275.52,
    "high": 277.53,
    "low": 272.55,
    "close": 276.15,
    "volume": 2532140,
    "date": "2025-10-14"
  },
  {
    "symbol": "ICE",
    "name": null,
    "open": 159.17,
    "high": 160.5,
    "low": 157.93,
    "close": 158.27,
    "volume": 2302422,
    "date": "2025-10-14"
  },
  {
    "symbol": "IDXX",
    "name": null,
    "open": 625.66,
    "high": 642.48,
    "low": 625.61,
    "close": 636.91,
    "volume": 322175,
    "date": "2025-10-14"
  },
  {
    "symbol": "IEX",
    "name": null,
    "open": 159.27,
    "high": 164.31,
    "low": 159.64,
    "close": 163.65,
    "volume": 295393,
    "date": "2025-10-14"
  },
  {
    "symbol": "IFF",
    "name": null,
    "open": 60.0,
    "high": 61.71,
    "low": 59.75,
    "close": 61.67,
    "volume": 1228825,
    "date": "2025-10-14"
  },
  {
    "symbol": "INCY",
    "name": null,
    "open": 84.38,
    "high": 86.16,
    "low": 83.5,
    "close": 85.96,
    "volume": 1242782,
    "date": "2025-10-14"
  },
  {
    "symbol": "INTC",
    "name": null,
    "open": 35.9,
    "high": 36.54,
    "low": 34.69,
    "close": 35.63,
    "volume": 116335441,
    "date": "2025-10-14"
  },
  {
    "symbol": "INTU",
    "name": null,
    "open": 645.82,
    "high": 660.71,
    "low": 644.45,
    "close": 657.16,
    "volume": 904325,
    "date": "2025-10-14"
  },
  {
    "symbol": "INVH",
    "name": null,
    "open": 28.27,
    "high": 28.64,
    "low": 28.27,
    "close": 28.51,
    "volume": 6084715,
    "date": "2025-10-14"
  },
  {
    "symbol": "IP",
    "name": null,
    "open": 45.35,
    "high": 47.17,
    "low": 45.12,
    "close": 46.67,
    "volume": 4244075,
    "date": "2025-10-14"
  },
  {
    "symbol": "IPG",
    "name": null,
    "open": 25.92,
    "high": 26.8,
    "low": 25.76,
    "close": 26.79,
    "volume": 6725886,
    "date": "2025-10-14"
  },
  {
    "symbol": "IQV",
    "name": null,
    "open": 202.1,
    "high": 207.04,
    "low": 200.03,
    "close": 204.76,
    "volume": 1224472,
    "date": "2025-10-14"
  },
  {
    "symbol": "IR",
    "name": null,
    "open": 74.78,
    "high": 77.59,
    "low": 74.42,
    "close": 77.24,
    "volume": 3352655,
    "date": "2025-10-14"
  },
  {
    "symbol": "IRM",
    "name": null,
    "open": 101.39,
    "high": 103.37,
    "low": 100.88,
    "close": 103.36,
    "volume": 707020,
    "date": "2025-10-14"
  },
  {
    "symbol": "ISRG",
    "name": null,
    "open": 430.3,
    "high": 439.2,
    "low": 427.84,
    "close": 436.39,
    "volume": 2048744,
    "date": "2025-10-14"
  },
  {
    "symbol": "IT",
    "name": null,
    "open": 243.29,
    "high": 249.45,
    "low": 241.36,
    "close": 246.73,
    "volume": 555128,
    "date": "2025-10-14"
  },
  {
    "symbol": "ITW",
    "name": null,
    "open": 242.75,
    "high": 249.53,
    "low": 242.53,
    "close": 248.09,
    "volume": 916582,
    "date": "2025-10-14"
  },
  {
    "symbol": "IVZ",
    "name": null,
    "open": 22.93,
    "high": 23.75,
    "low": 22.75,
    "close": 23.45,
    "volume": 6479021,
    "date": "2025-10-14"
  },
  {
    "symbol": "J",
    "name": null,
    "open": 152.0,
    "high": 158.02,
    "low": 151.96,
    "close": 158.02,
    "volume": 856530,
    "date": "2025-10-14"
  },
  {
    "symbol": "JBHT",
    "name": null,
    "open": 137.11,
    "high": 139.85,
    "low": 136.58,
    "close": 139.37,
    "volume": 946221,
    "date": "2025-10-14"
  },
  {
    "symbol": "JBL",
    "name": null,
    "open": 196.73,
    "high": 202.45,
    "low": 195.0,
    "close": 200.59,
    "volume": 819436,
    "date": "2025-10-14"
  },
  {
    "symbol": "JCI",
    "name": null,
    "open": 105.0,
    "high": 108.25,
    "low": 104.49,
    "close": 107.85,
    "volume": 2069989,
    "date": "2025-10-14"
  },
  {
    "symbol": "JKHY",
    "name": null,
    "open": 151.99,
    "high": 155.08,
    "low": 151.54,
    "close": 154.12,
    "volume": 1037434,
    "date": "2025-10-14"
  },
  {
    "symbol": "JNJ",
    "name": null,
    "open": 192.92,
    "high": 194.39,
    "low": 185.88,
    "close": 190.85,
    "volume": 11272499,
    "date": "2025-10-14"
  },
  {
    "symbol": "JPM",
    "name": null,
    "open": 305.84,
    "high": 306.83,
    "low": 294.21,
    "close": 302.08,
    "volume": 14136235,
    "date": "2025-10-14"
  },
  {
    "symbol": "K",
    "name": null,
    "open": 82.8,
    "high": 82.95,
    "low": 82.8,
    "close": 82.95,
    "volume": 1712343,
    "date": "2025-10-14"
  },
  {
    "symbol": "KDP",
    "name": null,
    "open": 26.33,
    "high": 26.74,
    "low": 26.09,
    "close": 26.69,
    "volume": 17078910,
    "date": "2025-10-14"
  },
  {
    "symbol": "KEY",
    "name": null,
    "open": 17.47,
    "high": 18.22,
    "low": 17.47,
    "close": 18.01,
    "volume": 22842681,
    "date": "2025-10-14"
  },
  {
    "symbol": "KEYS",
    "name": null,
    "open": 160.77,
    "high": 166.29,
    "low": 160.51,
    "close": 164.84,
    "volume": 765958,
    "date": "2025-10-14"
  },
  {
    "symbol": "KHC",
    "name": null,
    "open": 25.06,
    "high": 25.47,
    "low": 25.04,
    "close": 25.44,
    "volume": 11231805,
    "date": "2025-10-14"
  },
  {
    "symbol": "KIM",
    "name": null,
    "open": 20.97,
    "high": 21.47,
    "low": 20.97,
    "close": 21.39,
    "volume": 3766944,
    "date": "2025-10-14"
  },
  {
    "symbol": "KKR",
    "name": null,
    "open": 119.21,
    "high": 127.15,
    "low": 118.67,
    "close": 125.98,
    "volume": 5394519,
    "date": "2025-10-14"
  },
  {
    "symbol": "KLAC",
    "name": null,
    "open": 998.55,
    "high": 1042.46,
    "low": 998.55,
    "close": 1025.71,
    "volume": 1046009,
    "date": "2025-10-14"
  },
  {
    "symbol": "KMB",
    "name": null,
    "open": 119.6,
    "high": 120.6,
    "low": 119.09,
    "close": 120.17,
    "volume": 1703307,
    "date": "2025-10-14"
  },
  {
    "symbol": "KMI",
    "name": null,
    "open": 27.09,
    "high": 27.38,
    "low": 27.0,
    "close": 27.31,
    "volume": 8824268,
    "date": "2025-10-14"
  },
  {
    "symbol": "KMX",
    "name": null,
    "open": 43.44,
    "high": 44.44,
    "low": 43.06,
    "close": 44.0,
    "volume": 3171899,
    "date": "2025-10-14"
  },
  {
    "symbol": "KO",
    "name": null,
    "open": 66.87,
    "high": 67.57,
    "low": 66.75,
    "close": 67.51,
    "volume": 11359159,
    "date": "2025-10-14"
  },
  {
    "symbol": "KR",
    "name": null,
    "open": 67.94,
    "high": 69.5,
    "low": 67.2,
    "close": 69.13,
    "volume": 5977776,
    "date": "2025-10-14"
  },
  {
    "symbol": "KVUE",
    "name": null,
    "open": 16.2,
    "high": 16.41,
    "low": 15.99,
    "close": 16.15,
    "volume": 15852288,
    "date": "2025-10-14"
  },
  {
    "symbol": "L",
    "name": null,
    "open": 101.75,
    "high": 102.73,
    "low": 101.26,
    "close": 102.62,
    "volume": 297532,
    "date": "2025-10-14"
  },
  {
    "symbol": "LDOS",
    "name": null,
    "open": 185.17,
    "high": 188.79,
    "low": 184.31,
    "close": 187.27,
    "volume": 395597,
    "date": "2025-10-14"
  },
  {
    "symbol": "LEN",
    "name": null,
    "open": 118.41,
    "high": 122.46,
    "low": 117.3,
    "close": 122.23,
    "volume": 3713416,
    "date": "2025-10-14"
  },
  {
    "symbol": "LH",
    "name": null,
    "open": 276.0,
    "high": 280.83,
    "low": 276.05,
    "close": 279.78,
    "volume": 254490,
    "date": "2025-10-14"
  },
  {
    "symbol": "LHX",
    "name": null,
    "open": 292.82,
    "high": 300.61,
    "low": 292.5,
    "close": 299.99,
    "volume": 695551,
    "date": "2025-10-14"
  },
  {
    "symbol": "LII",
    "name": null,
    "open": 520.22,
    "high": 532.04,
    "low": 517.37,
    "close": 530.84,
    "volume": 300705,
    "date": "2025-10-14"
  },
  {
    "symbol": "LIN",
    "name": null,
    "open": 453.25,
    "high": 462.07,
    "low": 453.07,
    "close": 459.25,
    "volume": 1598517,
    "date": "2025-10-14"
  },
  {
    "symbol": "LKQ",
    "name": null,
    "open": 28.78,
    "high": 29.89,
    "low": 28.76,
    "close": 29.83,
    "volume": 1908463,
    "date": "2025-10-14"
  },
  {
    "symbol": "LLY",
    "name": null,
    "open": 822.09,
    "high": 821.91,
    "low": 806.32,
    "close": 812.35,
    "volume": 1487086,
    "date": "2025-10-14"
  },
  {
    "symbol": "LMT",
    "name": null,
    "open": 501.25,
    "high": 507.0,
    "low": 499.0,
    "close": 505.18,
    "volume": 951392,
    "date": "2025-10-14"
  },
  {
    "symbol": "LNT",
    "name": null,
    "open": 68.04,
    "high": 68.61,
    "low": 67.78,
    "close": 68.33,
    "volume": 1816561,
    "date": "2025-10-14"
  },
  {
    "symbol": "LOW",
    "name": null,
    "open": 233.92,
    "high": 241.74,
    "low": 233.23,
    "close": 240.75,
    "volume": 2370914,
    "date": "2025-10-14"
  },
  {
    "symbol": "LRCX",
    "name": null,
    "open": 134.31,
    "high": 140.92,
    "low": 134.05,
    "close": 138.31,
    "volume": 10452623,
    "date": "2025-10-14"
  },
  {
    "symbol": "LULU",
    "name": null,
    "open": 167.47,
    "high": 171.35,
    "low": 165.56,
    "close": 169.13,
    "volume": 3096175,
    "date": "2025-10-14"
  },
  {
    "symbol": "LUV",
    "name": null,
    "open": 31.52,
    "high": 33.62,
    "low": 31.42,
    "close": 33.42,
    "volume": 8111690,
    "date": "2025-10-14"
  },
  {
    "symbol": "LVS",
    "name": null,
    "open": 45.91,
    "high": 48.41,
    "low": 45.91,
    "close": 48.04,
    "volume": 5464505,
    "date": "2025-10-14"
  },
  {
    "symbol": "LW",
    "name": null,
    "open": 63.34,
    "high": 64.25,
    "low": 62.94,
    "close": 64.16,
    "volume": 1100537,
    "date": "2025-10-14"
  },
  {
    "symbol": "LYB",
    "name": null,
    "open": 45.2,
    "high": 46.93,
    "low": 45.07,
    "close": 46.66,
    "volume": 3564267,
    "date": "2025-10-14"
  },
  {
    "symbol": "LYV",
    "name": null,
    "open": 152.85,
    "high": 154.01,
    "low": 151.7,
    "close": 152.83,
    "volume": 1276357,
    "date": "2025-10-14"
  },
  {
    "symbol": "MA",
    "name": null,
    "open": 556.0,
    "high": 569.71,
    "low": 556.0,
    "close": 567.92,
    "volume": 2121250,
    "date": "2025-10-14"
  },
  {
    "symbol": "MAA",
    "name": null,
    "open": 134.48,
    "high": 135.05,
    "low": 133.24,
    "close": 133.76,
    "volume": 715217,
    "date": "2025-10-14"
  },
  {
    "symbol": "MAR",
    "name": null,
    "open": 260.89,
    "high": 269.64,
    "low": 260.42,
    "close": 267.97,
    "volume": 1298575,
    "date": "2025-10-14"
  },
  {
    "symbol": "MAS",
    "name": null,
    "open": 65.57,
    "high": 68.44,
    "low": 65.41,
    "close": 68.13,
    "volume": 1600017,
    "date": "2025-10-14"
  },
  {
    "symbol": "MCD",
    "name": null,
    "open": 300.16,
    "high": 305.52,
    "low": 300.11,
    "close": 304.56,
    "volume": 2422738,
    "date": "2025-10-14"
  },
  {
    "symbol": "MCHP",
    "name": null,
    "open": 62.25,
    "high": 66.61,
    "low": 62.22,
    "close": 64.6,
    "volume": 8646043,
    "date": "2025-10-14"
  },
  {
    "symbol": "MCK",
    "name": null,
    "open": 773.0,
    "high": 783.89,
    "low": 762.25,
    "close": 781.9,
    "volume": 499753,
    "date": "2025-10-14"
  },
  {
    "symbol": "MCO",
    "name": null,
    "open": 472.13,
    "high": 483.38,
    "low": 471.61,
    "close": 481.25,
    "volume": 839491,
    "date": "2025-10-14"
  },
  {
    "symbol": "MDLZ",
    "name": null,
    "open": 61.31,
    "high": 62.19,
    "low": 60.84,
    "close": 62.13,
    "volume": 5577303,
    "date": "2025-10-14"
  },
  {
    "symbol": "MDT",
    "name": null,
    "open": 95.26,
    "high": 96.6,
    "low": 95.4,
    "close": 96.54,
    "volume": 3945265,
    "date": "2025-10-14"
  },
  {
    "symbol": "MET",
    "name": null,
    "open": 80.2,
    "high": 83.2,
    "low": 80.1,
    "close": 82.89,
    "volume": 1976601,
    "date": "2025-10-14"
  },
  {
    "symbol": "META",
    "name": null,
    "open": 708.0,
    "high": 715.54,
    "low": 699.33,
    "close": 708.65,
    "volume": 8679816,
    "date": "2025-10-14"
  },
  {
    "symbol": "MGM",
    "name": null,
    "open": 31.65,
    "high": 32.99,
    "low": 31.26,
    "close": 32.45,
    "volume": 4301321,
    "date": "2025-10-14"
  },
  {
    "symbol": "MHK",
    "name": null,
    "open": 118.04,
    "high": 125.79,
    "low": 117.97,
    "close": 125.71,
    "volume": 718893,
    "date": "2025-10-14"
  },
  {
    "symbol": "MKC",
    "name": null,
    "open": 64.65,
    "high": 65.88,
    "low": 64.09,
    "close": 65.8,
    "volume": 1953676,
    "date": "2025-10-14"
  },
  {
    "symbol": "MLM",
    "name": null,
    "open": 638.61,
    "high": 657.17,
    "low": 632.92,
    "close": 656.85,
    "volume": 275972,
    "date": "2025-10-14"
  },
  {
    "symbol": "MMC",
    "name": null,
    "open": 205.77,
    "high": 207.28,
    "low": 204.51,
    "close": 207.02,
    "volume": 1658092,
    "date": "2025-10-14"
  },
  {
    "symbol": "MMM",
    "name": null,
    "open": 149.27,
    "high": 153.69,
    "low": 149.28,
    "close": 152.53,
    "volume": 2128546,
    "date": "2025-10-14"
  },
  {
    "symbol": "MNST",
    "name": null,
    "open": 67.15,
    "high": 68.89,
    "low": 67.01,
    "close": 68.61,
    "volume": 6078474,
    "date": "2025-10-14"
  },
  {
    "symbol": "MO",
    "name": null,
    "open": 65.0,
    "high": 65.87,
    "low": 64.84,
    "close": 65.4,
    "volume": 5314122,
    "date": "2025-10-14"
  },
  {
    "symbol": "MOH",
    "name": null,
    "open": 192.32,
    "high": 196.14,
    "low": 191.7,
    "close": 194.89,
    "volume": 713686,
    "date": "2025-10-14"
  },
  {
    "symbol": "MOS",
    "name": null,
    "open": 30.52,
    "high": 30.76,
    "low": 29.85,
    "close": 29.95,
    "volume": 4931351,
    "date": "2025-10-14"
  },
  {
    "symbol": "MPC",
    "name": null,
    "open": 181.41,
    "high": 186.09,
    "low": 181.39,
    "close": 183.12,
    "volume": 1024876,
    "date": "2025-10-14"
  },
  {
    "symbol": "MPWR",
    "name": null,
    "open": 967.54,
    "high": 994.83,
    "low": 960.0,
    "close": 968.25,
    "volume": 752815,
    "date": "2025-10-14"
  },
  {
    "symbol": "MRK",
    "name": null,
    "open": 85.38,
    "high": 85.68,
    "low": 84.15,
    "close": 84.7,
    "volume": 6901481,
    "date": "2025-10-14"
  },
  {
    "symbol": "MRNA",
    "name": null,
    "open": 26.33,
    "high": 26.69,
    "low": 26.01,
    "close": 26.25,
    "volume": 7020794,
    "date": "2025-10-14"
  },
  {
    "symbol": "MS",
    "name": null,
    "open": 154.5,
    "high": 157.12,
    "low": 151.88,
    "close": 155.34,
    "volume": 7129768,
    "date": "2025-10-14"
  },
  {
    "symbol": "MSCI",
    "name": null,
    "open": 547.85,
    "high": 556.89,
    "low": 546.99,
    "close": 553.58,
    "volume": 290252,
    "date": "2025-10-14"
  },
  {
    "symbol": "MSFT",
    "name": null,
    "open": 509.85,
    "high": 515.28,
    "low": 506.0,
    "close": 513.57,
    "volume": 14368234,
    "date": "2025-10-14"
  },
  {
    "symbol": "MSI",
    "name": null,
    "open": 458.93,
    "high": 464.33,
    "low": 457.11,
    "close": 460.62,
    "volume": 382901,
    "date": "2025-10-14"
  },
  {
    "symbol": "MTB",
    "name": null,
    "open": 182.3,
    "high": 188.69,
    "low": 181.77,
    "close": 187.04,
    "volume": 907088,
    "date": "2025-10-14"
  },
  {
    "symbol": "MTCH",
    "name": null,
    "open": 31.8,
    "high": 32.51,
    "low": 31.61,
    "close": 32.44,
    "volume": 2626763,
    "date": "2025-10-14"
  },
  {
    "symbol": "MTD",
    "name": null,
    "open": 1270.55,
    "high": 1313.29,
    "low": 1275.58,
    "close": 1303.04,
    "volume": 175106,
    "date": "2025-10-14"
  },
  {
    "symbol": "MU",
    "name": null,
    "open": 186.96,
    "high": 192.46,
    "low": 186.25,
    "close": 187.06,
    "volume": 15425337,
    "date": "2025-10-14"
  },
  {
    "symbol": "NCLH",
    "name": null,
    "open": 22.55,
    "high": 23.99,
    "low": 22.46,
    "close": 23.75,
    "volume": 9789701,
    "date": "2025-10-14"
  },
  {
    "symbol": "NDAQ",
    "name": null,
    "open": 88.93,
    "high": 90.17,
    "low": 88.92,
    "close": 89.54,
    "volume": 2490800,
    "date": "2025-10-14"
  },
  {
    "symbol": "NDSN",
    "name": null,
    "open": 227.81,
    "high": 234.93,
    "low": 225.32,
    "close": 233.37,
    "volume": 169783,
    "date": "2025-10-14"
  },
  {
    "symbol": "NEE",
    "name": null,
    "open": 84.17,
    "high": 84.84,
    "low": 83.43,
    "close": 84.64,
    "volume": 7258740,
    "date": "2025-10-14"
  },
  {
    "symbol": "NEM",
    "name": null,
    "open": 87.7,
    "high": 91.24,
    "low": 87.7,
    "close": 90.54,
    "volume": 7882650,
    "date": "2025-10-14"
  },
  {
    "symbol": "NFLX",
    "name": null,
    "open": 1214.75,
    "high": 1224.29,
    "low": 1203.1,
    "close": 1215.35,
    "volume": 2325540,
    "date": "2025-10-14"
  },
  {
    "symbol": "NI",
    "name": null,
    "open": 42.67,
    "high": 43.22,
    "low": 42.62,
    "close": 42.93,
    "volume": 2981533,
    "date": "2025-10-14"
  },
  {
    "symbol": "NKE",
    "name": null,
    "open": 66.47,
    "high": 68.0,
    "low": 66.06,
    "close": 67.64,
    "volume": 8169500,
    "date": "2025-10-14"
  },
  {
    "symbol": "NOC",
    "name": null,
    "open": 619.48,
    "high": 627.41,
    "low": 618.23,
    "close": 626.93,
    "volume": 299947,
    "date": "2025-10-14"
  },
  {
    "symbol": "NOW",
    "name": null,
    "open": 907.35,
    "high": 924.27,
    "low": 897.36,
    "close": 911.26,
    "volume": 707692,
    "date": "2025-10-14"
  },
  {
    "symbol": "NRG",
    "name": null,
    "open": 165.57,
    "high": 168.98,
    "low": 163.09,
    "close": 165.61,
    "volume": 1680534,
    "date": "2025-10-14"
  },
  {
    "symbol": "NSC",
    "name": null,
    "open": 287.68,
    "high": 292.11,
    "low": 287.0,
    "close": 290.31,
    "volume": 447853,
    "date": "2025-10-14"
  },
  {
    "symbol": "NTAP",
    "name": null,
    "open": 116.94,
    "high": 121.72,
    "low": 116.94,
    "close": 120.55,
    "volume": 2309618,
    "date": "2025-10-14"
  },
  {
    "symbol": "NTRS",
    "name": null,
    "open": 126.37,
    "high": 130.67,
    "low": 126.28,
    "close": 129.02,
    "volume": 864325,
    "date": "2025-10-14"
  },
  {
    "symbol": "NUE",
    "name": null,
    "open": 135.35,
    "high": 139.74,
    "low": 134.35,
    "close": 138.51,
    "volume": 1087777,
    "date": "2025-10-14"
  },
  {
    "symbol": "NVDA",
    "name": null,
    "open": 184.78,
    "high": 184.8,
    "low": 179.7,
    "close": 180.03,
    "volume": 201606600,
    "date": "2025-10-14"
  },
  {
    "symbol": "NVR",
    "name": null,
    "open": 7535.55,
    "high": 7779.98,
    "low": 7532.67,
    "close": 7737.01,
    "volume": 22068,
    "date": "2025-10-14"
  },
  {
    "symbol": "NWS",
    "name": null,
    "open": 29.55,
    "high": 29.95,
    "low": 29.5,
    "close": 29.95,
    "volume": 528555,
    "date": "2025-10-14"
  },
  {
    "symbol": "NWSA",
    "name": null,
    "open": 25.92,
    "high": 26.66,
    "low": 25.91,
    "close": 26.64,
    "volume": 4106173,
    "date": "2025-10-14"
  },
  {
    "symbol": "NXPI",
    "name": null,
    "open": 211.68,
    "high": 219.69,
    "low": 210.8,
    "close": 216.11,
    "volume": 2232909,
    "date": "2025-10-14"
  },
  {
    "symbol": "O",
    "name": null,
    "open": 58.73,
    "high": 59.09,
    "low": 58.56,
    "close": 58.84,
    "volume": 3644877,
    "date": "2025-10-14"
  },
  {
    "symbol": "ODFL",
    "name": null,
    "open": 134.71,
    "high": 137.48,
    "low": 134.03,
    "close": 135.43,
    "volume": 2623194,
    "date": "2025-10-14"
  },
  {
    "symbol": "OKE",
    "name": null,
    "open": 68.65,
    "high": 69.95,
    "low": 68.26,
    "close": 69.58,
    "volume": 2614459,
    "date": "2025-10-14"
  },
  {
    "symbol": "OMC",
    "name": null,
    "open": 75.76,
    "high": 78.61,
    "low": 75.7,
    "close": 78.55,
    "volume": 3330155,
    "date": "2025-10-14"
  },
  {
    "symbol": "ON",
    "name": null,
    "open": 48.75,
    "high": 51.19,
    "low": 48.69,
    "close": 49.54,
    "volume": 7890123,
    "date": "2025-10-14"
  },
  {
    "symbol": "ORCL",
    "name": null,
    "open": 303.57,
    "high": 304.42,
    "low": 291.99,
    "close": 299.0,
    "volume": 14773290,
    "date": "2025-10-14"
  },
  {
    "symbol": "ORLY",
    "name": null,
    "open": 103.06,
    "high": 104.06,
    "low": 102.31,
    "close": 103.05,
    "volume": 3996906,
    "date": "2025-10-14"
  },
  {
    "symbol": "OTIS",
    "name": null,
    "open": 89.08,
    "high": 90.91,
    "low": 88.7,
    "close": 90.82,
    "volume": 1766541,
    "date": "2025-10-14"
  },
  {
    "symbol": "OXY",
    "name": null,
    "open": 41.94,
    "high": 42.53,
    "low": 41.52,
    "close": 42.28,
    "volume": 8311698,
    "date": "2025-10-14"
  },
  {
    "symbol": "PANW",
    "name": null,
    "open": 209.76,
    "high": 210.8,
    "low": 206.7,
    "close": 207.56,
    "volume": 4114166,
    "date": "2025-10-14"
  },
  {
    "symbol": "PAYC",
    "name": null,
    "open": 199.48,
    "high": 203.06,
    "low": 200.13,
    "close": 200.53,
    "volume": 378462,
    "date": "2025-10-14"
  },
  {
    "symbol": "PAYX",
    "name": null,
    "open": 127.55,
    "high": 129.2,
    "low": 127.08,
    "close": 128.59,
    "volume": 2440207,
    "date": "2025-10-14"
  },
  {
    "symbol": "PCAR",
    "name": null,
    "open": 92.44,
    "high": 95.78,
    "low": 92.25,
    "close": 95.11,
    "volume": 2101731,
    "date": "2025-10-14"
  },
  {
    "symbol": "PCG",
    "name": null,
    "open": 16.0,
    "high": 16.67,
    "low": 15.95,
    "close": 16.4,
    "volume": 21877070,
    "date": "2025-10-14"
  },
  {
    "symbol": "PEG",
    "name": null,
    "open": 81.51,
    "high": 83.32,
    "low": 81.49,
    "close": 82.44,
    "volume": 1992244,
    "date": "2025-10-14"
  },
  {
    "symbol": "PEP",
    "name": null,
    "open": 148.71,
    "high": 151.62,
    "low": 148.5,
    "close": 151.54,
    "volume": 8240970,
    "date": "2025-10-14"
  },
  {
    "symbol": "PFE",
    "name": null,
    "open": 24.65,
    "high": 24.79,
    "low": 24.48,
    "close": 24.52,
    "volume": 38864944,
    "date": "2025-10-14"
  },
  {
    "symbol": "PFG",
    "name": null,
    "open": 78.89,
    "high": 81.9,
    "low": 78.5,
    "close": 81.29,
    "volume": 805226,
    "date": "2025-10-14"
  },
  {
    "symbol": "PG",
    "name": null,
    "open": 147.57,
    "high": 149.25,
    "low": 147.08,
    "close": 149.16,
    "volume": 5017464,
    "date": "2025-10-14"
  },
  {
    "symbol": "PGR",
    "name": null,
    "open": 236.37,
    "high": 240.99,
    "low": 236.54,
    "close": 240.4,
    "volume": 2116303,
    "date": "2025-10-14"
  },
  {
    "symbol": "PH",
    "name": null,
    "open": 717.56,
    "high": 743.89,
    "low": 717.02,
    "close": 736.48,
    "volume": 254509,
    "date": "2025-10-14"
  },
  {
    "symbol": "PHM",
    "name": null,
    "open": 119.76,
    "high": 125.33,
    "low": 119.39,
    "close": 124.89,
    "volume": 2163290,
    "date": "2025-10-14"
  },
  {
    "symbol": "PKG",
    "name": null,
    "open": 206.28,
    "high": 212.26,
    "low": 204.88,
    "close": 210.76,
    "volume": 532219,
    "date": "2025-10-14"
  },
  {
    "symbol": "PLD",
    "name": null,
    "open": 112.55,
    "high": 115.71,
    "low": 111.81,
    "close": 115.45,
    "volume": 2361344,
    "date": "2025-10-14"
  },
  {
    "symbol": "PLTR",
    "name": null,
    "open": 176.0,
    "high": 182.34,
    "low": 170.82,
    "close": 179.74,
    "volume": 48784139,
    "date": "2025-10-14"
  },
  {
    "symbol": "PM",
    "name": null,
    "open": 158.43,
    "high": 161.15,
    "low": 157.95,
    "close": 159.07,
    "volume": 4717238,
    "date": "2025-10-14"
  },
  {
    "symbol": "PNC",
    "name": null,
    "open": 184.63,
    "high": 190.4,
    "low": 184.5,
    "close": 189.73,
    "volume": 2475287,
    "date": "2025-10-14"
  },
  {
    "symbol": "PNR",
    "name": null,
    "open": 107.7,
    "high": 110.76,
    "low": 107.25,
    "close": 110.41,
    "volume": 706124,
    "date": "2025-10-14"
  },
  {
    "symbol": "PNW",
    "name": null,
    "open": 92.44,
    "high": 93.73,
    "low": 92.17,
    "close": 93.45,
    "volume": 723792,
    "date": "2025-10-14"
  },
  {
    "symbol": "PODD",
    "name": null,
    "open": 314.16,
    "high": 323.69,
    "low": 312.68,
    "close": 318.3,
    "volume": 352845,
    "date": "2025-10-14"
  },
  {
    "symbol": "POOL",
    "name": null,
    "open": 288.64,
    "high": 299.51,
    "low": 288.36,
    "close": 295.46,
    "volume": 565923,
    "date": "2025-10-14"
  },
  {
    "symbol": "PPG",
    "name": null,
    "open": 98.0,
    "high": 101.34,
    "low": 97.99,
    "close": 100.5,
    "volume": 1094954,
    "date": "2025-10-14"
  },
  {
    "symbol": "PPL",
    "name": null,
    "open": 37.56,
    "high": 37.96,
    "low": 37.44,
    "close": 37.86,
    "volume": 2751521,
    "date": "2025-10-14"
  },
  {
    "symbol": "PRU",
    "name": null,
    "open": 100.6,
    "high": 104.36,
    "low": 100.55,
    "close": 103.7,
    "volume": 1182689,
    "date": "2025-10-14"
  },
  {
    "symbol": "PSA",
    "name": null,
    "open": 299.83,
    "high": 304.27,
    "low": 299.85,
    "close": 302.15,
    "volume": 842308,
    "date": "2025-10-14"
  },
  {
    "symbol": "PSKY",
    "name": null,
    "open": 16.96,
    "high": 17.44,
    "low": 16.63,
    "close": 17.29,
    "volume": 4213216,
    "date": "2025-10-14"
  },
  {
    "symbol": "PSX",
    "name": null,
    "open": 128.13,
    "high": 132.97,
    "low": 127.67,
    "close": 130.84,
    "volume": 1516773,
    "date": "2025-10-14"
  },
  {
    "symbol": "PTC",
    "name": null,
    "open": 199.81,
    "high": 203.08,
    "low": 199.67,
    "close": 202.06,
    "volume": 506051,
    "date": "2025-10-14"
  },
  {
    "symbol": "PWR",
    "name": null,
    "open": 423.81,
    "high": 438.93,
    "low": 420.56,
    "close": 431.6,
    "volume": 711475,
    "date": "2025-10-14"
  },
  {
    "symbol": "PYPL",
    "name": null,
    "open": 67.4,
    "high": 69.71,
    "low": 66.77,
    "close": 69.15,
    "volume": 12358295,
    "date": "2025-10-14"
  },
  {
    "symbol": "QCOM",
    "name": null,
    "open": 159.3,
    "high": 164.26,
    "low": 159.26,
    "close": 161.74,
    "volume": 8368156,
    "date": "2025-10-14"
  },
  {
    "symbol": "RCL",
    "name": null,
    "open": 303.0,
    "high": 317.62,
    "low": 301.75,
    "close": 313.86,
    "volume": 1378331,
    "date": "2025-10-14"
  },
  {
    "symbol": "REG",
    "name": null,
    "open": 71.35,
    "high": 72.09,
    "low": 71.19,
    "close": 71.81,
    "volume": 878159,
    "date": "2025-10-14"
  },
  {
    "symbol": "REGN",
    "name": null,
    "open": 556.92,
    "high": 576.18,
    "low": 553.86,
    "close": 572.6,
    "volume": 1004590,
    "date": "2025-10-14"
  },
  {
    "symbol": "RF",
    "name": null,
    "open": 24.32,
    "high": 25.3,
    "low": 24.29,
    "close": 25.16,
    "volume": 44164321,
    "date": "2025-10-14"
  },
  {
    "symbol": "RJF",
    "name": null,
    "open": 158.35,
    "high": 164.45,
    "low": 158.49,
    "close": 162.54,
    "volume": 658991,
    "date": "2025-10-14"
  },
  {
    "symbol": "RL",
    "name": null,
    "open": 312.73,
    "high": 320.0,
    "low": 309.85,
    "close": 317.92,
    "volume": 426320,
    "date": "2025-10-14"
  },
  {
    "symbol": "RMD",
    "name": null,
    "open": 268.56,
    "high": 272.18,
    "low": 267.0,
    "close": 270.07,
    "volume": 678510,
    "date": "2025-10-14"
  },
  {
    "symbol": "ROK",
    "name": null,
    "open": 335.31,
    "high": 349.09,
    "low": 335.17,
    "close": 344.01,
    "volume": 831131,
    "date": "2025-10-14"
  },
  {
    "symbol": "ROL",
    "name": null,
    "open": 56.28,
    "high": 56.96,
    "low": 55.89,
    "close": 56.89,
    "volume": 1460093,
    "date": "2025-10-14"
  },
  {
    "symbol": "ROP",
    "name": null,
    "open": 508.4,
    "high": 515.32,
    "low": 506.79,
    "close": 513.82,
    "volume": 678053,
    "date": "2025-10-14"
  },
  {
    "symbol": "ROST",
    "name": null,
    "open": 154.66,
    "high": 156.55,
    "low": 154.25,
    "close": 155.26,
    "volume": 1987735,
    "date": "2025-10-14"
  },
  {
    "symbol": "RSG",
    "name": null,
    "open": 223.3,
    "high": 226.2,
    "low": 222.78,
    "close": 224.48,
    "volume": 783504,
    "date": "2025-10-14"
  },
  {
    "symbol": "RTX",
    "name": null,
    "open": 158.2,
    "high": 160.58,
    "low": 157.29,
    "close": 159.4,
    "volume": 2163755,
    "date": "2025-10-14"
  },
  {
    "symbol": "RVTY",
    "name": null,
    "open": 90.11,
    "high": 92.16,
    "low": 88.75,
    "close": 91.14,
    "volume": 1010680,
    "date": "2025-10-14"
  },
  {
    "symbol": "SBAC",
    "name": null,
    "open": 188.3,
    "high": 192.47,
    "low": 188.3,
    "close": 191.07,
    "volume": 1241687,
    "date": "2025-10-14"
  },
  {
    "symbol": "SBUX",
    "name": null,
    "open": 79.21,
    "high": 81.48,
    "low": 79.03,
    "close": 81.15,
    "volume": 7425831,
    "date": "2025-10-14"
  },
  {
    "symbol": "SCHW",
    "name": null,
    "open": 93.13,
    "high": 94.98,
    "low": 93.03,
    "close": 93.39,
    "volume": 6784266,
    "date": "2025-10-14"
  },
  {
    "symbol": "SHW",
    "name": null,
    "open": 329.78,
    "high": 337.04,
    "low": 329.25,
    "close": 335.27,
    "volume": 2600888,
    "date": "2025-10-14"
  },
  {
    "symbol": "SJM",
    "name": null,
    "open": 101.61,
    "high": 102.56,
    "low": 100.76,
    "close": 102.42,
    "volume": 1403019,
    "date": "2025-10-14"
  },
  {
    "symbol": "SLB",
    "name": null,
    "open": 31.75,
    "high": 32.76,
    "low": 31.69,
    "close": 32.57,
    "volume": 11310369,
    "date": "2025-10-14"
  },
  {
    "symbol": "SMCI",
    "name": null,
    "open": 54.13,
    "high": 55.21,
    "low": 52.98,
    "close": 53.11,
    "volume": 19590436,
    "date": "2025-10-14"
  },
  {
    "symbol": "SNA",
    "name": null,
    "open": 328.98,
    "high": 337.87,
    "low": 329.85,
    "close": 337.02,
    "volume": 343459,
    "date": "2025-10-14"
  },
  {
    "symbol": "SNPS",
    "name": null,
    "open": 436.41,
    "high": 452.8,
    "low": 433.36,
    "close": 443.76,
    "volume": 2886530,
    "date": "2025-10-14"
  },
  {
    "symbol": "SO",
    "name": null,
    "open": 98.7,
    "high": 99.81,
    "low": 98.47,
    "close": 99.68,
    "volume": 4196615,
    "date": "2025-10-14"
  },
  {
    "symbol": "SOLV",
    "name": null,
    "open": 70.4,
    "high": 71.61,
    "low": 70.4,
    "close": 71.49,
    "volume": 723077,
    "date": "2025-10-14"
  },
  {
    "symbol": "SPG",
    "name": null,
    "open": 176.24,
    "high": 176.54,
    "low": 174.65,
    "close": 175.83,
    "volume": 1243844,
    "date": "2025-10-14"
  },
  {
    "symbol": "SPGI",
    "name": null,
    "open": 477.1,
    "high": 488.29,
    "low": 477.0,
    "close": 486.69,
    "volume": 1086431,
    "date": "2025-10-14"
  },
  {
    "symbol": "SRE",
    "name": null,
    "open": 90.87,
    "high": 91.59,
    "low": 90.19,
    "close": 91.33,
    "volume": 2166796,
    "date": "2025-10-14"
  },
  {
    "symbol": "STE",
    "name": null,
    "open": 235.02,
    "high": 238.03,
    "low": 232.51,
    "close": 237.81,
    "volume": 384997,
    "date": "2025-10-14"
  },
  {
    "symbol": "STLD",
    "name": null,
    "open": 143.42,
    "high": 148.54,
    "low": 142.48,
    "close": 146.98,
    "volume": 918013,
    "date": "2025-10-14"
  },
  {
    "symbol": "STT",
    "name": null,
    "open": 113.16,
    "high": 116.02,
    "low": 113.19,
    "close": 115.4,
    "volume": 1472204,
    "date": "2025-10-14"
  },
  {
    "symbol": "STX",
    "name": null,
    "open": 215.49,
    "high": 217.4,
    "low": 210.57,
    "close": 211.63,
    "volume": 3641763,
    "date": "2025-10-14"
  },
  {
    "symbol": "STZ",
    "name": null,
    "open": 140.2,
    "high": 142.05,
    "low": 139.8,
    "close": 141.24,
    "volume": 1884162,
    "date": "2025-10-14"
  },
  {
    "symbol": "SW",
    "name": null,
    "open": 41.16,
    "high": 42.81,
    "low": 41.12,
    "close": 42.23,
    "volume": 3901473,
    "date": "2025-10-14"
  },
  {
    "symbol": "SWK",
    "name": null,
    "open": 63.24,
    "high": 67.36,
    "low": 63.2,
    "close": 67.02,
    "volume": 2261246,
    "date": "2025-10-14"
  },
  {
    "symbol": "SWKS",
    "name": null,
    "open": 71.33,
    "high": 73.64,
    "low": 71.25,
    "close": 72.77,
    "volume": 2271446,
    "date": "2025-10-14"
  },
  {
    "symbol": "SYF",
    "name": null,
    "open": 69.29,
    "high": 73.64,
    "low": 69.15,
    "close": 72.84,
    "volume": 4849561,
    "date": "2025-10-14"
  },
  {
    "symbol": "SYK",
    "name": null,
    "open": 364.3,
    "high": 372.95,
    "low": 364.27,
    "close": 370.0,
    "volume": 1038761,
    "date": "2025-10-14"
  },
  {
    "symbol": "SYY",
    "name": null,
    "open": 78.41,
    "high": 80.18,
    "low": 78.17,
    "close": 80.14,
    "volume": 1415242,
    "date": "2025-10-14"
  },
  {
    "symbol": "T",
    "name": null,
    "open": 25.58,
    "high": 26.15,
    "low": 25.58,
    "close": 26.13,
    "volume": 32388994,
    "date": "2025-10-14"
  },
  {
    "symbol": "TAP",
    "name": null,
    "open": 45.99,
    "high": 46.82,
    "low": 45.81,
    "close": 46.73,
    "volume": 1792814,
    "date": "2025-10-14"
  },
  {
    "symbol": "TDG",
    "name": null,
    "open": 1286.91,
    "high": 1322.27,
    "low": 1284.0,
    "close": 1312.48,
    "volume": 199088,
    "date": "2025-10-14"
  },
  {
    "symbol": "TDY",
    "name": null,
    "open": 562.37,
    "high": 577.55,
    "low": 565.72,
    "close": 571.93,
    "volume": 156523,
    "date": "2025-10-14"
  },
  {
    "symbol": "TECH",
    "name": null,
    "open": 58.73,
    "high": 60.08,
    "low": 58.15,
    "close": 59.27,
    "volume": 1557173,
    "date": "2025-10-14"
  },
  {
    "symbol": "TEL",
    "name": null,
    "open": 215.63,
    "high": 222.1,
    "low": 212.32,
    "close": 220.65,
    "volume": 1099745,
    "date": "2025-10-14"
  },
  {
    "symbol": "TER",
    "name": null,
    "open": 135.42,
    "high": 138.9,
    "low": 135.0,
    "close": 136.97,
    "volume": 2973786,
    "date": "2025-10-14"
  },
  {
    "symbol": "TFC",
    "name": null,
    "open": 42.64,
    "high": 44.24,
    "low": 42.62,
    "close": 43.93,
    "volume": 8421102,
    "date": "2025-10-14"
  },
  {
    "symbol": "TGT",
    "name": null,
    "open": 86.53,
    "high": 89.4,
    "low": 86.36,
    "close": 88.96,
    "volume": 5483185,
    "date": "2025-10-14"
  },
  {
    "symbol": "TJX",
    "name": null,
    "open": 141.41,
    "high": 144.36,
    "low": 141.16,
    "close": 144.1,
    "volume": 3592261,
    "date": "2025-10-14"
  },
  {
    "symbol": "TKO",
    "name": null,
    "open": 187.43,
    "high": 193.07,
    "low": 186.72,
    "close": 189.97,
    "volume": 612582,
    "date": "2025-10-14"
  },
  {
    "symbol": "TMO",
    "name": null,
    "open": 521.74,
    "high": 529.85,
    "low": 519.45,
    "close": 525.83,
    "volume": 1234291,
    "date": "2025-10-14"
  },
  {
    "symbol": "TMUS",
    "name": null,
    "open": 230.0,
    "high": 230.65,
    "low": 226.98,
    "close": 229.42,
    "volume": 3772514,
    "date": "2025-10-14"
  },
  {
    "symbol": "TPL",
    "name": null,
    "open": 874.3,
    "high": 920.71,
    "low": 865.63,
    "close": 907.52,
    "volume": 122106,
    "date": "2025-10-14"
  },
  {
    "symbol": "TPR",
    "name": null,
    "open": 112.65,
    "high": 117.31,
    "low": 111.35,
    "close": 116.26,
    "volume": 1682980,
    "date": "2025-10-14"
  },
  {
    "symbol": "TRGP",
    "name": null,
    "open": 148.97,
    "high": 151.63,
    "low": 147.4,
    "close": 150.38,
    "volume": 1472945,
    "date": "2025-10-14"
  },
  {
    "symbol": "TRMB",
    "name": null,
    "open": 75.65,
    "high": 78.64,
    "low": 75.4,
    "close": 78.04,
    "volume": 975178,
    "date": "2025-10-14"
  },
  {
    "symbol": "TROW",
    "name": null,
    "open": 104.48,
    "high": 107.19,
    "low": 104.25,
    "close": 106.13,
    "volume": 1190818,
    "date": "2025-10-14"
  },
  {
    "symbol": "TRV",
    "name": null,
    "open": 270.32,
    "high": 275.77,
    "low": 271.3,
    "close": 275.64,
    "volume": 907786,
    "date": "2025-10-14"
  },
  {
    "symbol": "TSCO",
    "name": null,
    "open": 54.85,
    "high": 55.72,
    "low": 54.45,
    "close": 55.48,
    "volume": 3764218,
    "date": "2025-10-14"
  },
  {
    "symbol": "TSLA",
    "name": null,
    "open": 426.79,
    "high": 434.2,
    "low": 417.86,
    "close": 429.24,
    "volume": 71541278,
    "date": "2025-10-14"
  },
  {
    "symbol": "TSN",
    "name": null,
    "open": 51.58,
    "high": 52.93,
    "low": 51.07,
    "close": 52.85,
    "volume": 2389885,
    "date": "2025-10-14"
  },
  {
    "symbol": "TT",
    "name": null,
    "open": 414.17,
    "high": 425.05,
    "low": 411.59,
    "close": 424.04,
    "volume": 1218477,
    "date": "2025-10-14"
  },
  {
    "symbol": "TTD",
    "name": null,
    "open": 50.25,
    "high": 51.25,
    "low": 49.45,
    "close": 50.73,
    "volume": 8067464,
    "date": "2025-10-14"
  },
  {
    "symbol": "TTWO",
    "name": null,
    "open": 256.99,
    "high": 260.73,
    "low": 254.55,
    "close": 257.72,
    "volume": 899230,
    "date": "2025-10-14"
  },
  {
    "symbol": "TXN",
    "name": null,
    "open": 171.97,
    "high": 176.27,
    "low": 171.45,
    "close": 173.94,
    "volume": 9750217,
    "date": "2025-10-14"
  },
  {
    "symbol": "TXT",
    "name": null,
    "open": 81.53,
    "high": 84.04,
    "low": 80.65,
    "close": 83.76,
    "volume": 755337,
    "date": "2025-10-14"
  },
  {
    "symbol": "TYL",
    "name": null,
    "open": 503.64,
    "high": 507.75,
    "low": 500.39,
    "close": 506.28,
    "volume": 222108,
    "date": "2025-10-14"
  },
  {
    "symbol": "UAL",
    "name": null,
    "open": 97.93,
    "high": 103.85,
    "low": 97.2,
    "close": 103.15,
    "volume": 6232232,
    "date": "2025-10-14"
  },
  {
    "symbol": "UBER",
    "name": null,
    "open": 93.78,
    "high": 95.18,
    "low": 92.46,
    "close": 94.25,
    "volume": 8356342,
    "date": "2025-10-14"
  },
  {
    "symbol": "UDR",
    "name": null,
    "open": 36.12,
    "high": 36.44,
    "low": 36.04,
    "close": 36.36,
    "volume": 2224004,
    "date": "2025-10-14"
  },
  {
    "symbol": "UHS",
    "name": null,
    "open": 196.85,
    "high": 204.4,
    "low": 195.76,
    "close": 203.81,
    "volume": 328637,
    "date": "2025-10-14"
  },
  {
    "symbol": "ULTA",
    "name": null,
    "open": 541.51,
    "high": 551.5,
    "low": 537.95,
    "close": 541.01,
    "volume": 532925,
    "date": "2025-10-14"
  },
  {
    "symbol": "UNH",
    "name": null,
    "open": 354.95,
    "high": 362.33,
    "low": 353.4,
    "close": 359.93,
    "volume": 5856287,
    "date": "2025-10-14"
  },
  {
    "symbol": "UNP",
    "name": null,
    "open": 223.92,
    "high": 227.85,
    "low": 223.33,
    "close": 227.08,
    "volume": 1656666,
    "date": "2025-10-14"
  },
  {
    "symbol": "UPS",
    "name": null,
    "open": 82.5,
    "high": 84.3,
    "low": 82.0,
    "close": 84.05,
    "volume": 5263381,
    "date": "2025-10-14"
  },
  {
    "symbol": "URI",
    "name": null,
    "open": 960.87,
    "high": 1007.97,
    "low": 955.42,
    "close": 1000.5,
    "volume": 246080,
    "date": "2025-10-14"
  },
  {
    "symbol": "USB",
    "name": null,
    "open": 45.99,
    "high": 47.36,
    "low": 45.93,
    "close": 47.09,
    "volume": 6776071,
    "date": "2025-10-14"
  },
  {
    "symbol": "V",
    "name": null,
    "open": 341.0,
    "high": 350.0,
    "low": 340.25,
    "close": 348.38,
    "volume": 3389381,
    "date": "2025-10-14"
  },
  {
    "symbol": "VICI",
    "name": null,
    "open": 30.93,
    "high": 31.25,
    "low": 30.9,
    "close": 31.12,
    "volume": 5391124,
    "date": "2025-10-14"
  },
  {
    "symbol": "VLO",
    "name": null,
    "open": 159.11,
    "high": 163.66,
    "low": 159.12,
    "close": 162.19,
    "volume": 1274650,
    "date": "2025-10-14"
  },
  {
    "symbol": "VLTO",
    "name": null,
    "open": 101.04,
    "high": 102.16,
    "low": 100.82,
    "close": 101.99,
    "volume": 1162494,
    "date": "2025-10-14"
  },
  {
    "symbol": "VMC",
    "name": null,
    "open": 301.67,
    "high": 310.68,
    "low": 301.73,
    "close": 309.07,
    "volume": 554569,
    "date": "2025-10-14"
  },
  {
    "symbol": "VRSK",
    "name": null,
    "open": 242.89,
    "high": 245.68,
    "low": 241.9,
    "close": 243.36,
    "volume": 904839,
    "date": "2025-10-14"
  },
  {
    "symbol": "VRSN",
    "name": null,
    "open": 262.92,
    "high": 267.68,
    "low": 262.77,
    "close": 265.01,
    "volume": 653209,
    "date": "2025-10-14"
  },
  {
    "symbol": "VRTX",
    "name": null,
    "open": 406.08,
    "high": 415.55,
    "low": 405.45,
    "close": 412.22,
    "volume": 1030319,
    "date": "2025-10-14"
  },
  {
    "symbol": "VST",
    "name": null,
    "open": 205.79,
    "high": 208.85,
    "low": 201.4,
    "close": 205.51,
    "volume": 2999081,
    "date": "2025-10-14"
  },
  {
    "symbol": "VTR",
    "name": null,
    "open": 67.62,
    "high": 68.16,
    "low": 67.36,
    "close": 67.96,
    "volume": 1329689,
    "date": "2025-10-14"
  },
  {
    "symbol": "VTRS",
    "name": null,
    "open": 9.75,
    "high": 9.97,
    "low": 9.74,
    "close": 9.93,
    "volume": 6451815,
    "date": "2025-10-14"
  },
  {
    "symbol": "VZ",
    "name": null,
    "open": 39.8,
    "high": 40.58,
    "low": 39.76,
    "close": 40.55,
    "volume": 22250622,
    "date": "2025-10-14"
  },
  {
    "symbol": "WAB",
    "name": null,
    "open": 191.69,
    "high": 196.54,
    "low": 191.27,
    "close": 196.0,
    "volume": 444406,
    "date": "2025-10-14"
  },
  {
    "symbol": "WAT",
    "name": null,
    "open": 332.97,
    "high": 338.37,
    "low": 332.29,
    "close": 333.14,
    "volume": 510418,
    "date": "2025-10-14"
  },
  {
    "symbol": "WBD",
    "name": null,
    "open": 17.33,
    "high": 18.17,
    "low": 17.35,
    "close": 17.98,
    "volume": 17495541,
    "date": "2025-10-14"
  },
  {
    "symbol": "WDAY",
    "name": null,
    "open": 233.71,
    "high": 238.97,
    "low": 232.86,
    "close": 237.18,
    "volume": 1754248,
    "date": "2025-10-14"
  },
  {
    "symbol": "WDC",
    "name": null,
    "open": 116.11,
    "high": 117.28,
    "low": 112.52,
    "close": 113.13,
    "volume": 7825981,
    "date": "2025-10-14"
  },
  {
    "symbol": "WEC",
    "name": null,
    "open": 115.64,
    "high": 117.2,
    "low": 115.18,
    "close": 116.49,
    "volume": 1628232,
    "date": "2025-10-14"
  },
  {
    "symbol": "WELL",
    "name": null,
    "open": 166.88,
    "high": 169.48,
    "low": 166.95,
    "close": 169.34,
    "volume": 2368007,
    "date": "2025-10-14"
  },
  {
    "symbol": "WFC",
    "name": null,
    "open": 82.52,
    "high": 86.06,
    "low": 80.4,
    "close": 84.56,
    "volume": 31774904,
    "date": "2025-10-14"
  },
  {
    "symbol": "WM",
    "name": null,
    "open": 217.46,
    "high": 219.2,
    "low": 216.82,
    "close": 218.11,
    "volume": 1058672,
    "date": "2025-10-14"
  },
  {
    "symbol": "WMB",
    "name": null,
    "open": 62.06,
    "high": 62.79,
    "low": 61.95,
    "close": 62.36,
    "volume": 3704629,
    "date": "2025-10-14"
  },
  {
    "symbol": "WMT",
    "name": null,
    "open": 104.05,
    "high": 107.92,
    "low": 102.91,
    "close": 107.21,
    "volume": 27286416,
    "date": "2025-10-14"
  },
  {
    "symbol": "WRB",
    "name": null,
    "open": 77.81,
    "high": 78.48,
    "low": 77.27,
    "close": 78.46,
    "volume": 1189287,
    "date": "2025-10-14"
  },
  {
    "symbol": "WSM",
    "name": null,
    "open": 187.67,
    "high": 192.73,
    "low": 185.1,
    "close": 191.5,
    "volume": 799823,
    "date": "2025-10-14"
  },
  {
    "symbol": "WST",
    "name": null,
    "open": 261.61,
    "high": 263.22,
    "low": 260.6,
    "close": 261.17,
    "volume": 401957,
    "date": "2025-10-14"
  },
  {
    "symbol": "WTW",
    "name": null,
    "open": 337.76,
    "high": 345.1,
    "low": 337.76,
    "close": 343.31,
    "volume": 349417,
    "date": "2025-10-14"
  },
  {
    "symbol": "WY",
    "name": null,
    "open": 23.76,
    "high": 24.14,
    "low": 23.54,
    "close": 23.9,
    "volume": 6387762,
    "date": "2025-10-14"
  },
  {
    "symbol": "WYNN",
    "name": null,
    "open": 112.0,
    "high": 117.5,
    "low": 111.97,
    "close": 116.11,
    "volume": 1293743,
    "date": "2025-10-14"
  },
  {
    "symbol": "XEL",
    "name": null,
    "open": 80.41,
    "high": 81.46,
    "low": 80.36,
    "close": 80.85,
    "volume": 3523873,
    "date": "2025-10-14"
  },
  {
    "symbol": "XOM",
    "name": null,
    "open": 110.75,
    "high": 112.96,
    "low": 110.73,
    "close": 112.29,
    "volume": 7662729,
    "date": "2025-10-14"
  },
  {
    "symbol": "XYL",
    "name": null,
    "open": 144.52,
    "high": 147.48,
    "low": 144.0,
    "close": 146.57,
    "volume": 691773,
    "date": "2025-10-14"
  },
  {
    "symbol": "XYZ",
    "name": null,
    "open": 73.22,
    "high": 77.44,
    "low": 71.92,
    "close": 76.18,
    "volume": 5224717,
    "date": "2025-10-14"
  },
  {
    "symbol": "YUM",
    "name": null,
    "open": 139.65,
    "high": 144.62,
    "low": 139.29,
    "close": 143.98,
    "volume": 1698072,
    "date": "2025-10-14"
  },
  {
    "symbol": "ZBH",
    "name": null,
    "open": 94.61,
    "high": 98.74,
    "low": 94.62,
    "close": 98.37,
    "volume": 1125520,
    "date": "2025-10-14"
  },
  {
    "symbol": "ZBRA",
    "name": null,
    "open": 277.0,
    "high": 291.0,
    "low": 277.0,
    "close": 288.99,
    "volume": 494623,
    "date": "2025-10-14"
  },
  {
    "symbol": "ZTS",
    "name": null,
    "open": 141.55,
    "high": 143.52,
    "low": 141.11,
    "close": 143.46,
    "volume": 2336639,
    "date": "2025-10-14"
  }
]